rtl/cond_decoder.v
module cond_decoder(input clk, reset, pc_s, reg_write, mem_write,
                    input [3:0] cond, alu_flags, flag_w,
                    output reg pc_src, reg_write_en, mem_write_en
                    );


    wire [3:0] flags;
    wire [3:0] flag_en;
    reg cond_ex;

    dff z_ff(.clk(clk), .reset(reset), .en(flag_en[3]), .d(alu_flags[3]), .q(flags[3]));
    dff n_ff(.clk(clk), .reset(reset), .en(flag_en[2]), .d(alu_flags[2]), .q(flags[2]));
    dff c_ff(.clk(clk), .reset(reset), .en(flag_en[1]), .d(alu_flags[1]), .q(flags[1]));
    dff v_ff(.clk(clk), .reset(reset), .en(flag_en[0]), .d(alu_flags[0]), .q(flags[0]));

    assign mem_write_en = cond_ex & mem_write;
    assign reg_write_en = cond_ex & reg_write;
    assign pc_src = cond_ex & pc_s;
    assign flag_en = flag_w & (4{cond_ex});

    cond_check cond_check_i (
        .cond(cond),
        .Z(flags[3]),
        .N(flags[2]),
        .C(flags[1]),
        .V(flags[0]),
        .cond_ex(cond_ex)
    );

endmodule




module cond_check(input [3:0] cond,
                  input Z, N, C, V
                  output reg cond_ex
                );

    always @(*)begin
        case(cond)
            4'b0000: cond_ex = Z;
            4'b0001: cond_ex = ~Z;
            4'b0010: cond_ex = C;
            4'b0011: cond_ex = ~C;
            4'b0100: cond_ex = N;
            4'b0101: cond_ex = ~N;
            4'b0110: cond_ex = V;
            4'b0111: cond_ex = ~V;
            4'b1000: cond_ex = C & ~Z;
            4'b1001: cond_ex = C | ~Z;
            4'b1010: cond_ex = (N == V);
            4'b1011: cond_ex = (N != V);
            4'b1100: cond_ex = ~Z & (N == V);
            4'b1101: cond_ex = Z | (N != V);
            4'b1110: cond_ex = 1'b1;
            default: cond_ex = 1'b0;
        endcase
    end


endmodule


module dff(
    input clk,
    input reset,
    input en,
    input d,
    output reg q
);

    always @(posedge clk or posedge reset) begin
        if (reset)
            q <= 1'b0;
        else if (en)
            q <= d;
    end

endmodule

tb/units/tb_cond_check.v
`timescale 1ns/1ps

module cond_check_tb;

    reg [3:0] cond;
    reg Z, N, C, V, expected;
    wire cond_ex;
    integer inc;

    cond_check uut(.cond(cond),
                    .Z(Z),
                    .N(N),
                    .C(C),
                    .V(V),
                    .cond_ex(cond_ex)
                    );

    function ref_model;
        input [3:0] cond;
        input Z, N, C, V;

        begin
            case(cond)
                4'b0000: ref_model = Z;
                4'b0001: ref_model = ~Z;
                4'b0010: ref_model = C;
                4'b0011: ref_model = ~C;
                4'b0100: ref_model = N;
                4'b0101: ref_model = ~N;
                4'b0110: ref_model = V;
                4'b0111: ref_model = ~V;
                4'b1000: ref_model = C & ~Z;
                4'b1001: ref_model = C | ~Z;
                4'b1010: ref_model = (N == V);
                4'b1011: ref_model = (N != V);
                4'b1100: ref_model = ~Z & (N == V);
                4'b1101: ref_model = Z | (N != V);
                4'b1110: ref_model = 1'b1;
                default: ref_model = 1'b0;
            endcase
        end
    endfunction



    initial begin
        $dumpfile("sim/waves/cond_check.vcd");
        $dumpvars(0, cond_check_tb);

        for (inc = 0; inc < 16; inc = inc + 1) begin

            V = inc[0];
            C = inc[1];
            N = inc[2];
            Z = inc[3];
            cond = inc;

            expected = ref_model(cond, Z, N, C, V);
            #1;

            if (cond_ex !== expected) begin
                    $display("FAIL cond=%b Z=%b N=%b C=%b V=%b expected=%b got=%b",
                             cond,Z,N,C,V,
                             expected,cond_ex);
                end
         end
        
        $display("DONE");
        $finish;
    end


endmodule

sim/waves/cond_check.vcd
$date
	Thu Jul  2 05:36:59 2026
$end
$version
	Icarus Verilog
$end
$timescale
	1ps
$end
$scope module cond_check_tb $end
$var wire 1 ! cond_ex $end
$var reg 1 " C $end
$var reg 1 # N $end
$var reg 1 $ V $end
$var reg 1 % Z $end
$var reg 4 & cond [3:0] $end
$var reg 1 ' expected $end
$var integer 32 ( inc [31:0] $end
$scope function ref_model $end
$var reg 1 ) C $end
$var reg 1 * N $end
$var reg 1 + V $end
$var reg 1 , Z $end
$var reg 4 - cond [3:0] $end
$upscope $end
$scope module uut $end
$var wire 1 " C $end
$var wire 1 # N $end
$var wire 1 $ V $end
$var wire 1 % Z $end
$var wire 4 . cond [3:0] $end
$var reg 1 ! cond_ex $end
$upscope $end
$upscope $end
$enddefinitions $end
$comment Show the parameter values. $end
$dumpall
$end
#0
$dumpvars
b0 .
b0 -
0,
0+
0*
0)
b0 (
0'
b0 &
0%
0$
0#
0"
0!
$end
#1000
1!
1'
b1 -
1+
b1 &
b1 .
1$
b1 (
#2000
b10 -
1)
0+
b10 &
b10 .
1"
0$
b10 (
#3000
0!
0'
b11 -
1+
b11 &
b11 .
1$
b11 (
#4000
1!
1'
b100 -
1*
0)
0+
b100 &
b100 .
1#
0"
0$
b100 (
#5000
0!
0'
b101 -
1+
b101 &
b101 .
1$
b101 (
#6000
b110 -
1)
0+
b110 &
b110 .
1"
0$
b110 (
#7000
b111 -
1+
b111 &
b111 .
1$
b111 (
#8000
b1000 -
1,
0*
0)
0+
b1000 &
b1000 .
1%
0#
0"
0$
b1000 (
#9000
b1001 -
1+
b1001 &
b1001 .
1$
b1001 (
#10000
1!
1'
b1010 -
1)
0+
b1010 &
b1010 .
1"
0$
b1010 (
#11000
b1011 -
1+
b1011 &
b1011 .
1$
b1011 (
#12000
0!
0'
b1100 -
1*
0)
0+
b1100 &
b1100 .
1#
0"
0$
b1100 (
#13000
1!
1'
b1101 -
1+
b1101 &
b1101 .
1$
b1101 (
#14000
b1110 -
1)
0+
b1110 &
b1110 .
1"
0$
b1110 (
#15000
0!
0'
b1111 -
1+
b1111 &
b1111 .
1$
b1111 (
#16000
b10000 (
