rtl/cond_decoder.v
module cond_decoder(input clk, reset, pc_s, reg_write, mem_write,
                    input [3:0] cond, alu_flags, flag_w,
                    output reg pc_src, reg_write_en, mem_write_en
                    );


    wire [3:0] flags;
    wire [3:0] flag_en;
    reg cond_ex;

    dff z_ff(.clk(clk), .reset(reset), .en(flag_en[3]), .d(alu_flags[3]), .q(flags[3]));
    dff n_ff(.clk(clk), .reset(reset), .en(flag_en[2]), .d(alu_flags[2]), .q(flags[2]));
    dff c_ff(.clk(clk), .reset(reset), .en(flag_en[1]), .d(alu_flags[1]), .q(flags[1]));
    dff v_ff(.clk(clk), .reset(reset), .en(flag_en[0]), .d(alu_flags[0]), .q(flags[0]));

    assign mem_write_en = cond_ex & mem_write;
    assign reg_write_en = cond_ex & reg_write;
    assign pc_src = cond_ex & pc_s;
    assign flag_en = flag_w & (4{cond_ex});

    cond_check cond_check_i (
        .cond(cond),
        .Z(flags[3]),
        .N(flags[2]),
        .C(flags[1]),
        .V(flags[0]),
        .cond_ex(cond_ex)
    );

endmodule




module cond_check(input [3:0] cond,
                  input Z, N, C, V
                  output reg cond_ex
                );

    always @(*)begin
        case(cond)
            4'b0000: cond_ex = Z;
            4'b0001: cond_ex = ~Z;
            4'b0010: cond_ex = C;
            4'b0011: cond_ex = ~C;
            4'b0100: cond_ex = N;
            4'b0101: cond_ex = ~N;
            4'b0110: cond_ex = V;
            4'b0111: cond_ex = ~V;
            4'b1000: cond_ex = C & ~Z;
            4'b1001: cond_ex = C | ~Z;
            4'b1010: cond_ex = (N == V);
            4'b1011: cond_ex = (N != V);
            4'b1100: cond_ex = ~Z & (N == V);
            4'b1101: cond_ex = Z | (N != V);
            4'b1110: cond_ex = 1'b1;
            default: cond_ex = 1'b0;
        endcase
    end


endmodule


module dff(
    input clk,
    input reset,
    input en,
    input d,
    output reg q
);

    always @(posedge clk or posedge reset) begin
        if (reset)
            q <= 1'b0;
        else if (en)
            q <= d;
    end

endmodule

rtl/decoder.v
module decoder(input [1:0] op,
                    input [5:0] funct,
                    input [3:0] rd,
                    output reg [3:0] flag_en,
                    output reg [2:0] alu_control,
                    output reg [1:0] imm_src,
                    output reg pc_s, reg_src_a, reg_src_b, mem_to_reg, alu_src,
                    output reg reg_write, mem_write
                    );

    reg alu_op, branch;
    reg [9:0] contr_sigs;


// main decoder
    always @(*) begin
        case(op)
            2'b00: if (funct[5]) contr_sigs = 10'b0001100010;
                    else contr_sigs = 10'b0000100010;
            2'b01: if (funct[0]) contr_sigs = 10'b0001010110;
                    else contr_sigs = 10'b0101000101;
            2'b10: contr_sigs = 10'b1011001000;
            default: contr_sigs = 10'b0;
        endcase
    
        {reg_src_a, reg_src_b, branch, alu_src, alu_op, mem_to_reg, imm_src, reg_write, mem_write} = contr_sigs;
    end



// Alu decoder
    always @(*) begin
        if (alu_op) begin
            case(funct[4:1])
                4'b0000: alu_control = 3'b000; // and
                4'b0001: alu_control = 3'b001; // or
                4'b0010: alu_control = 3'b010; // add
                4'b0011: alu_control = 3'b011; // sub
                4'b0100: alu_control = 3'b100; // xor
                default: alu_control = 3'b0;
            endcase
            flag_en[0] = funct[0] & (alu_control == 3'b010 | alu_control == 3'b011);
            flag_en[1] = funct[0] & (alu_control == 3'b010 | alu_control == 3'b011);
            flag_en[2] = funct[0];
            flag_en[3] = funct[0];
        end

        else begin
            alu_control = 3'b010;
            flag_en = 4'b0;
        end
    end


    always @(*) begin
        pc_s = ((rd == 4'b1111) && reg_write) | branch;
    end


endmodule

rtl/controller.v
module controller(input clk, reset, 
                  input [31:12] instr,
                  input [3:0] alu_flags,
                  output reg reg_write_en, mem_write_en, pc_src, reg_src_a, reg_src_b, mem_to_reg, alu_src,
                  output [2:0] alu_control, 
                  output [1:0] imm_src,
                );

    wire [3:0] flag_w;
    wire mem_write, reg_write, pc_s;

   decoder decoder_i(.op(instr[27:0]), .funct(instr[25:20]), .rd([15:12]),
                      .flag_en(flag_w), .alu_control(alu_control), .imm_src(imm_src)
                      .pc_s(pc_s), .reg_src_a(reg_src_a), .reg_src_b(reg_src_b),
                      .mem_to_reg(mem_to_reg), .alu_src(alu_src), .reg_write(reg_write)
                      .mem_write(mem_write) 
                      );


   cond_decoder cond_logic(.clk(clk), .reset(reset), .pc_s(pc_s), .reg_write(reg_write),
                            .mem_write(mem_write), .cond(instr[31:28]), .alu_flags(alu_flags),
                            .flag_w(flag_w), .pc_src(pc_src), .reg_write_en(reg_write_en), .mem_write_en(mem_write_en)
                            );

endmodule

tb/integration/tb_controller.sv
`timescale 1ns/1ps

module controller_tb;

    logic clk, reset;
    logic [3:0] alu_flags;
    logic [31:12] instr;
    logic [2:0] alu_control;
    logic [1:0] imm_src;
    logic reg_write_en, mem_write_en, pc_src, reg_src_a, reg_src_b, mem_to_reg, alu_src;

    localparam CLK_PERIOD = 1;
    localparam TESTS_NO = 11;

    /// Expected control transaction
    typedef struct packed {
        logic reg_write_en, mem_write_en, pc_src;
        logic reg_src_a, reg_src_b, mem_to_reg, alu_src;
        logic [2:0] alu_control;
        logic [1:0] imm_src;
    } control_signals;

    typedef struct packed{

        logic [31:12] instr;
        logic [3:0] alu_flags;

    } test_case;

    control_signals expected;



    controller dut(.clk(clk),
                    .reset(reset),
                    .instr(instr),
                    .alu_flags(alu_flags),
                    .alu_control(alu_control),
                    .imm_src(imm_src),
                    .reg_write_en(reg_write_en),
                    .mem_write_en(mem_write_en),
                    .pc_src(pc_src),
                    .reg_src_a(reg_src_a),
                    .reg_src_b(reg_src_b),
                    .mem_to_reg(mem_to_reg),
                    .alu_src(alu_src)
                    );

    initial begin
            clk = 0;
            forever #CLK_PERIOD clk = ~clk;
        end


    // Reset Dut
    task automatic reset_dut;
        begin

            instr = 0;
            alu_flags = 0;
            reset = 1;
            repeat(2) @(posedge clk);
            reset = 0;

        end
    endtask

    // Driver - Apply inputs
    task automatic drive(input logic [31:12] instr_i,
                          input logic [3:0]  alu_flags_i);
        begin

            @(negedge clk);
            instr = instr_i;
            alu_flags = alu_flags_i;
        end
    endtask

    // checker
    task automatic check_outputs(input control_signals control_sigs);

        begin

            @(posedge clk)
            assert ((control_sigs.pc_src ==  pc_src)) // program counter source // 
                $display("[%0t] PASS", $time);
            else
                 $error("Expected pc_src=%0b Got=%0b", control_sigs.pc_src, pc_src);
            
            assert ((control_sigs.reg_write_en ==  reg_write_en)) 
                $display("[%0t] PASS", $time);
            else
                 $error("Expected reg_write_en=%0b Got=%0b", control_sigs.reg_write_en, reg_write_en);

            assert ((control_sigs.mem_write_en ==  mem_write_en)) 
                $display("[%0t] PASS", $time);
            else
                 $error("Expected mem_write_en=%0b Got=%0b", control_sigs.mem_write_en, mem_write_en);

             assert ((control_sigs.reg_src_a ==  reg_src_a)) 
                $display("[%0t] PASS", $time);
            else
                 $error("Expected reg_src_a=%0b Got=%0b", control_sigs.reg_src_a, reg_src_a);

             assert ((control_sigs.reg_src_b ==  reg_src_b)) 
                $display("[%0t] PASS", $time);
            else
                 $error("Expected reg_src_b=%0b Got=%0b", control_sigs.reg_src_b, reg_src_b);

             assert ((control_sigs.mem_to_reg ==  mem_to_reg)) 
                $display("[%0t] PASS", $time);
            else
                 $error("Expected mem_write_en=%0b Got=%0b", control_sigs.mem_to_reg, mem_to_reg);
            
            assert ((control_sigs.alu_src ==  alu_src)) 
                $display("[%0t] PASS", $time);
            else
                 $error("Expected alu_src=%0b Got=%0b", control_sigs.alu_src, alu_src);

            assert ((control_sigs.imm_src ==  imm_src)) 
                $display("[%0t] PASS", $time);
            else
                 $error("Expected imm_src=%0b Got=%0b", control_sigs.imm_src, imm_src);

            assert ((control_sigs.alu_control ==  alu_control)) 
                $display("[%0t] PASS", $time);
            else
                 $error("Expected alu_control=%0b Got=%0b", control_sigs.alu_control,  alu_control);

        end
    endtask
    
    
    // Test instruction cases 

        logic [31:12] instructions [TESTS_NO];
        logic [3:0] flags [TESTS_NO];
         
    initial begin

        instructions[0] = 20'b11100000010000000000; // ADD 
        flags[0] = 4'b0000;

        instructions[1] = 20'b11100000010100000000; // ADDS
        flags[1] = 4'b0001;

        instructions[2] = 20'b00000000010000000000; // ADDEQ
        flags[2] = 4'b0000;

        instructions[3] = 20'b00000000010100000000; // ADDSEQ
        flags[3] = 4'b1000;

        instructions[4] = 20'b11100010010100000000; // ADDIS
        flags[4] = 4'b0000;

        instructions[5] = 20'b00010000011100000000; // SUBSNEQ
        flags[5] = 4'b0111;

        instructions[6] = 20'b00100010000100000000; //ANDISC
        flags[6] = 4'b0000;

        instructions[7] = 20'b11100100000000000000; // STR
        flags[7] = 4'b0000;

        instructions[8] = 20'b11100100010100000000; // LDR
        flags[8] = 4'b0000;

        instructions[9] = 20'b11101000000000000000; // Branch
        flags[9] = 4'b0000;

        instructions[10] = 20'b11100000000000001111; // Branch (rd = 1111, reg_write =1)
        flags[10] = 4'b0000;


    end

    // Reference model
    function automatic control_signals ref_model(input logic [31:12] instr);

        control_signals control_sigs;
        begin
            case(instr)

                20'b11100000010000000000: begin  // ADD
                    control_sigs.alu_control = 3'b010;
                    control_sigs.alu_src = 1'b0;
                    control_sigs.imm_src = 2'b00;
                    control_sigs.mem_to_reg = 1'b0;
                    control_sigs.mem_write_en = 1'b0;
                    control_sigs.pc_src = 1'b0;
                    control_sigs.reg_src_a = 1'b0;
                    control_sigs.reg_src_b = 1'b0;
                    control_sigs.reg_write_en = 1'b1;
                end
                20'b11100000010100000000: begin // ADDS
                    control_sigs.alu_control = 3'b010;
                    control_sigs.alu_src = 1'b0;
                    control_sigs.imm_src = 2'b00;
                    control_sigs.mem_to_reg = 1'b0;
                    control_sigs.mem_write_en = 1'b0;
                    control_sigs.pc_src = 1'b0;
                    control_sigs.reg_src_a = 1'b0;
                    control_sigs.reg_src_b = 1'b0;
                    control_sigs.reg_write_en = 1'b1;
                end
               20'b00000000010000000000: begin // ADDEQ
                    control_sigs.alu_control = 3'b010;
                    control_sigs.alu_src = 1'b0;
                    control_sigs.imm_src = 2'b00;
                    control_sigs.mem_to_reg = 1'b0;
                    control_sigs.mem_write_en = 1'b0;
                    control_sigs.pc_src = 1'b0;
                    control_sigs.reg_src_a = 1'b0;
                    control_sigs.reg_src_b = 1'b0;
                    control_sigs.reg_write_en = 1'b0;
                end
                20'b00000000010100000000: begin // ADDSEQ
                    control_sigs.alu_control = 3'b010;
                    control_sigs.alu_src = 1'b0;
                    control_sigs.imm_src = 2'b00;
                    control_sigs.mem_to_reg = 1'b0;
                    control_sigs.mem_write_en = 1'b0;
                    control_sigs.pc_src = 1'b0;
                    control_sigs.reg_src_a = 1'b0;
                    control_sigs.reg_src_b = 1'b0;
                    control_sigs.reg_write_en = 1'b0;
                end
                20'b11100010010100000000: begin // ADDIS
                    control_sigs.alu_control = 3'b010;
                    control_sigs.alu_src = 1'b1;
                    control_sigs.imm_src = 2'b00;
                    control_sigs.mem_to_reg = 1'b0;
                    control_sigs.mem_write_en = 1'b0;
                    control_sigs.pc_src = 1'b0;
                    control_sigs.reg_src_a = 1'b0;
                    control_sigs.reg_src_b = 1'b0;
                    control_sigs.reg_write_en = 1'b1;
                end
                 20'b00010000011100000000: begin // SUBSNEQ
                    control_sigs.alu_control = 3'b011;
                    control_sigs.alu_src = 1'b0;
                    control_sigs.imm_src = 2'b00;
                    control_sigs.mem_to_reg = 1'b0;
                    control_sigs.mem_write_en = 1'b0;
                    control_sigs.pc_src = 1'b0;
                    control_sigs.reg_src_a = 1'b0;
                    control_sigs.reg_src_b = 1'b0;
                    control_sigs.reg_write_en = 1'b1;
                end
                20'b00100010000100000000: begin // ANDISC
                    control_sigs.alu_control = 3'b000;
                    control_sigs.alu_src = 1'b1;
                    control_sigs.imm_src = 2'b00;
                    control_sigs.mem_to_reg = 1'b0;
                    control_sigs.mem_write_en = 1'b0;
                    control_sigs.pc_src = 1'b0;
                    control_sigs.reg_src_a = 1'b0;
                    control_sigs.reg_src_b = 1'b0;
                    control_sigs.reg_write_en = 1'b1;
                end
                20'b11100100000000000000: begin // STR
                    control_sigs.alu_control = 3'b010;
                    control_sigs.alu_src = 1'b1;
                    control_sigs.imm_src = 2'b01;
                    control_sigs.mem_to_reg = 1'b0;
                    control_sigs.mem_write_en = 1'b1;
                    control_sigs.pc_src = 1'b0;
                    control_sigs.reg_src_a = 1'b0;
                    control_sigs.reg_src_b = 1'b1;
                    control_sigs.reg_write_en = 1'b0;
                end
                 20'b11100100010100000000: begin // LDR
                    control_sigs.alu_control = 3'b010;
                    control_sigs.alu_src = 1'b1;
                    control_sigs.imm_src = 2'b01;
                    control_sigs.mem_to_reg = 1'b1;
                    control_sigs.mem_write_en = 1'b0;
                    control_sigs.pc_src = 1'b0;
                    control_sigs.reg_src_a = 1'b0;
                    control_sigs.reg_src_b = 1'b0;
                    control_sigs.reg_write_en = 1'b1;
                end
                20'b11101000000000000000: begin // Branch
                    control_sigs.alu_control = 3'b010;
                    control_sigs.alu_src = 1'b1;
                    control_sigs.imm_src = 2'b10;
                    control_sigs.mem_to_reg = 1'b0;
                    control_sigs.mem_write_en = 1'b0;
                    control_sigs.pc_src = 1'b1;
                    control_sigs.reg_src_a = 1'b1;
                    control_sigs.reg_src_b = 1'b0;
                    control_sigs.reg_write_en = 1'b0;
                end
                20'b11100000000000001111: begin // Branch (rd = 1111, reg_write = 1)
                    control_sigs.alu_control = 3'b000;
                    control_sigs.alu_src = 1'b0;
                    control_sigs.imm_src = 2'b00;
                    control_sigs.mem_to_reg = 1'b0;
                    control_sigs.mem_write_en = 1'b0;
                    control_sigs.pc_src = 1'b1;
                    control_sigs.reg_src_a = 1'b0;
                    control_sigs.reg_src_b = 1'b0;
                    control_sigs.reg_write_en = 1'b1;
                end
                default: control_sigs = '0;
            endcase
        end

    return control_sigs;
        
    endfunction

    initial begin

        $dumpfile("sim/waves/controller.vcd");
        $dumpvars(0, controller_tb);

         reset_dut();

         for (int i = 0; i < 10; i++)
         begin
            drive( instructions[i],  flags[i]);
            $display("instruction code=%0b", instr);
            @(posedge clk);
          // expected
             expected = ref_model(instructions[i]);
            check_outputs(expected);
         end
        
        // implicit branch
        force dut.reg_write_en = 1;
        drive(instructions[10],  flags[10]);
        $display("instruction code=%0b", instr);
        @(posedge clk);
            expected = ref_model(instructions[10]);
        check_outputs(expected);
        release dut.reg_write_en;

          
        $display("DONE");
        $finish;
    end


endmodule

sim/waves/controller.vcd
$date
	Wed Jul  8 10:48:53 2026
$end
$version
	Icarus Verilog
$end
$timescale
	1ps
$end
$scope module controller_tb $end
$var wire 1 ! reg_write_en $end
$var wire 1 " reg_src_b $end
$var wire 1 # reg_src_a $end
$var wire 1 $ pc_src $end
$var wire 1 % mem_write_en $end
$var wire 1 & mem_to_reg $end
$var wire 2 ' imm_src [1:0] $end
$var wire 1 ( alu_src $end
$var wire 3 ) alu_control [2:0] $end
$var parameter 32 * CLK_PERIOD $end
$var parameter 32 + TESTS_NO $end
$var reg 4 , alu_flags [3:0] $end
$var reg 1 - clk $end
$var reg 12 . expected [11:0] $end
$var reg 20 / instr [31:12] $end
$var reg 1 0 reset $end
$scope function ref_model $end
$upscope $end
$scope module dut $end
$var wire 4 1 alu_flags [3:0] $end
$var wire 1 - clk $end
$var wire 20 2 instr [31:12] $end
$var wire 1 0 reset $end
$var wire 1 ! reg_write_en $end
$var wire 1 3 reg_write $end
$var wire 1 " reg_src_b $end
$var wire 1 # reg_src_a $end
$var wire 1 $ pc_src $end
$var wire 1 4 pc_s $end
$var wire 1 % mem_write_en $end
$var wire 1 5 mem_write $end
$var wire 1 & mem_to_reg $end
$var wire 2 6 imm_src [1:0] $end
$var wire 4 7 flag_w [3:0] $end
$var wire 1 ( alu_src $end
$var wire 3 8 alu_control [2:0] $end
$scope module cond_logic $end
$var wire 4 9 alu_flags [3:0] $end
$var wire 1 - clk $end
$var wire 4 : cond [3:0] $end
$var wire 4 ; flag_en [3:0] $end
$var wire 1 0 reset $end
$var wire 1 3 reg_write $end
$var wire 1 4 pc_s $end
$var wire 1 5 mem_write $end
$var wire 4 < flags [3:0] $end
$var wire 4 = flag_w [3:0] $end
$var wire 1 > cond_ex $end
$var reg 1 % mem_write_en $end
$var reg 1 $ pc_src $end
$var reg 1 ! reg_write_en $end
$scope module c_ff $end
$var wire 1 - clk $end
$var wire 1 ? d $end
$var wire 1 @ en $end
$var wire 1 0 reset $end
$var reg 1 A q $end
$upscope $end
$scope module cond_check_i $end
$var wire 1 B C $end
$var wire 1 C N $end
$var wire 1 D V $end
$var wire 1 E Z $end
$var wire 4 F cond [3:0] $end
$var reg 1 > cond_ex $end
$upscope $end
$scope module n_ff $end
$var wire 1 - clk $end
$var wire 1 G d $end
$var wire 1 H en $end
$var wire 1 0 reset $end
$var reg 1 I q $end
$upscope $end
$scope module v_ff $end
$var wire 1 - clk $end
$var wire 1 J d $end
$var wire 1 K en $end
$var wire 1 0 reset $end
$var reg 1 L q $end
$upscope $end
$scope module z_ff $end
$var wire 1 - clk $end
$var wire 1 M d $end
$var wire 1 N en $end
$var wire 1 0 reset $end
$var reg 1 O q $end
$upscope $end
$upscope $end
$scope module decoder_i $end
$var wire 6 P funct [5:0] $end
$var wire 2 Q op [1:0] $end
$var wire 4 R rd [3:0] $end
$var reg 3 S alu_control [2:0] $end
$var reg 1 T alu_op $end
$var reg 1 ( alu_src $end
$var reg 1 U branch $end
$var reg 10 V contr_sigs [9:0] $end
$var reg 4 W flag_en [3:0] $end
$var reg 2 X imm_src [1:0] $end
$var reg 1 & mem_to_reg $end
$var reg 1 5 mem_write $end
$var reg 1 4 pc_s $end
$var reg 1 # reg_src_a $end
$var reg 1 " reg_src_b $end
$var reg 1 3 reg_write $end
$upscope $end
$upscope $end
$scope begin $ivl_for_loop0 $end
$var integer 32 Y i [31:0] $end
$upscope $end
$scope task check_outputs $end
$upscope $end
$scope task drive $end
$upscope $end
$scope task reset_dut $end
$upscope $end
$upscope $end
$enddefinitions $end
$comment Show the parameter values. $end
$dumpall
b1011 +
b1 *
$end
#0
$dumpvars
b0 Y
b0 X
b0 W
b100010 V
0U
1T
b0 S
b0 R
b0 Q
b0 P
0O
0N
0M
0L
0K
0J
0I
0H
0G
b0 F
0E
0D
0C
0B
0A
0@
0?
0>
b0 =
b0 <
b0 ;
b0 :
b0 9
b0 8
b0 7
b0 6
05
04
13
b0 2
b0 1
10
b0 /
bx .
0-
b0 ,
b0 )
0(
b0 '
0&
0%
0$
0#
0"
0!
$end
#1000
1-
#2000
0-
#3000
00
1-
#4000
1!
b10 )
b10 8
b10 S
1>
b100 P
b1110 :
b1110 F
b11100000010000000000 /
b11100000010000000000 2
0-
#5000
b100000001000 .
1-
#6000
0-
#7000
b1 Y
1-
#8000
1N
1H
1@
1K
b1111 ;
b1111 7
b1111 =
b1111 W
1J
b101 P
b1 ,
b1 1
b1 9
b11100000010100000000 /
b11100000010100000000 2
0-
#9000
1D
b1 <
1L
1-
#10000
0-
#11000
b10 Y
1-
#12000
0N
0H
0@
0K
b0 ;
0!
b0 7
b0 =
b0 W
0>
0J
b100 P
b0 :
b0 F
b0 ,
b0 1
b0 9
b10000000000 /
b10000000000 2
0-
#13000
b1000 .
1-
#14000
0-
#15000
b11 Y
1-
#16000
b1111 7
b1111 =
b1111 W
1M
b101 P
b1000 ,
b1000 1
b1000 9
b10100000000 /
b10100000000 2
0-
#17000
1-
#18000
0-
#19000
b100 Y
1-
#20000
1N
1H
1@
1K
b1111 ;
1!
1(
b1100010 V
1>
0M
b100101 P
b1110 :
b1110 F
b0 ,
b0 1
b0 9
b11100010010100000000 /
b11100010010100000000 2
0-
#21000
0D
b0 <
0L
b100000101000 .
1-
#22000
0-
#23000
b101 Y
1-
#24000
b11 )
b11 8
b11 S
0(
b100010 V
1G
1?
1J
b111 P
b1 :
b1 F
b111 ,
b111 1
b111 9
b10000011100000000 /
b10000011100000000 2
0-
#25000
1D
1B
1C
1L
1A
b111 <
1I
b100000001100 .
1-
#26000
0-
#27000
b110 Y
1-
#28000
0@
0K
b1100 ;
b1100 7
b1100 =
b1100 W
b0 )
b0 8
b0 S
1(
b1100010 V
0G
0?
0J
b100001 P
b10 :
b10 F
b0 ,
b0 1
b0 9
b100010000100000000 /
b100010000100000000 2
0-
#29000
0C
b11 <
0I
b100000100000 .
1-
#30000
0-
#31000
b111 Y
1-
#32000
0N
0H
b0 ;
0!
1%
b0 7
b0 =
b0 W
b10 )
b10 8
b10 S
1"
0T
b1 '
b1 6
b1 X
03
15
b101000101 V
b1 Q
b0 P
b1110 :
b1110 F
b11100100000000000000 /
b11100100000000000000 2
0-
#33000
b10010101001 .
1-
#34000
0-
#35000
b1000 Y
1-
#36000
1!
0%
0"
1&
13
05
b1010110 V
b101 P
b11100100010100000000 /
b11100100010100000000 2
0-
#37000
b100001101001 .
1-
#38000
0-
#39000
b1001 Y
1-
#40000
1$
0!
14
1#
1U
0&
b10 '
b10 6
b10 X
03
b1011001000 V
b10 Q
b0 P
b11101000000000000000 /
b11101000000000000000 2
0-
#41000
b1100101010 .
1-
#42000
0-
#43000
1!
b1010 Y
1-
#44000
b0 )
b0 8
b0 S
1!
0#
0U
0(
1T
b0 '
b0 6
b0 X
13
b100010 V
b0 Q
b1111 R
b11100000000000001111 /
b11100000000000001111 2
0-
#45000
b101000000000 .
1-
#46000
0-
#47000
1!
1-
