rtl/alu.v
module alu(input [31:0] src_a, src_b,
           input [2:0] alu_control,
           output reg zero, negative, overflow, carry,
           output reg[31:0] alu_result
        );


    always @(*) begin
        case(alu_control)
        3'b000: begin
            alu_result = src_a & src_b;
            carry = 0;
            overflow = 0;
        end
        3'b001:begin
           alu_result = src_a | src_b;
           carry = 0;
           overflow = 0; 
        end
        3'b010: begin
            {carry, alu_result} = src_a + src_b;
            overflow = ((src_a[31] == src_b[31]) && (alu_result[31] != src_a[31]));
        end

         3'b011: begin
            {carry, alu_result} = src_a - src_b;
            overflow = ((src_a[31] != src_b[31]) && (alu_result[31] != src_a[31]));

        end
        3'b100:begin
           alu_result = src_a ^ src_b;
           carry = 0;
           overflow = 0; 
        end
        3'b101: begin
            alu_result = src_b;
            carry = 0;
            overflow = 0;
        end
        default: begin
            alu_result = 32'b0;
            carry = 0;
            overflow = 0;

        end

        endcase
    end

   always @(*) begin
    zero = (alu_result == 0);
    negative = alu_result[31];
    end

endmodule

rtl/mux.v
module mux2 #(parameter WIDTH = 8) (
    input  [WIDTH-1:0] data_1, data_2,
    input sel,
    output [WIDTH-1:0] out
    );

    assign out = sel? data_1 : data_2;


endmodule

rtl/extend.v
module extend(input [23:0] instr, 
              input [1:0] imm_src,
              output reg [31:0] ext_imm
            );

  always @(*) begin
    case(imm_src)
      2'b00: ext_imm = {24'b0, instr[7:0]};
      2'b01: ext_imm = {20'b0, instr[11:0]};
      2'b10: ext_imm = {{8{instr[23]}}, instr[23:0]} << 2;
      default: ext_imm = 32'b0;
    endcase
  end

endmodule

rtl/register.v
module reg_file(input clk, reg_write_en, 
                input[3:0] reg_addr_1, reg_addr_2, write_addr,
                input[31:0] write_data, reg_addr_15,
                output [31:0] read_data_1, read_data_2
                );

    reg [31:0] reg_file[14:0];
    

    always @(posedge clk) begin
        if (reg_write_en) 
            reg_file[write_addr] <= write_data;
    end
            
    assign read_data_1 = (reg_addr_1 == 4'b1111) ? reg_addr_15 : reg_file[reg_addr_1];
    assign read_data_2 = (reg_addr_2 == 4'b1111) ? reg_addr_15 : reg_file[reg_addr_2];

endmodule

rtl/adder.v
module adder(input [31:0] a, b,
             output [31:0] y
             );

    assign y = a + b;


endmodule

rtl/pc.v
module pc(input clk, reset,
          input [31:0] data,
          output reg [31:0] q
          );

    always @(posedge clk or posedge reset) begin
        if (reset) 
            q <= 0;

        else
            q <= data;
    end

endmodule

rtl/datapath.v
module datapath(input clk, reset, reg_write_en, mem_write_en, pc_src, reg_src_a, reg_src_b, mem_to_reg, alu_src,
                input [2:0] alu_control, 
                input [1:0] imm_src,
                output [3:0] alu_flags,
                output [31:0] write_data, alu_result, pc,
                input [31:0] read_data, instr
                );


    wire [3:0] reg_addr_1, reg_addr_2;
    wire [31:0] pc_next, pc_plus4, pc_plus8;
    wire [31:0] ext_imm, src_a, src_b, result;

    // program counter logic
    mux2 #(32) pc_mux(.data_1(result), .data_2(pc_plus4), .sel(pc_src), .out(pc_next));
    pc pc_flops(.clk(clk), .reset(reset), .data(pc_next), .q(pc));
    adder plus4_adder(.a(pc), .b(32'b100), .y(pc_plus4));
    adder plus8_adder(.a(pc_plus4), .b(32'b100), .y(pc_plus8));


    // register file logc
    mux2 #(4) reg_addr1_mux(.data_1(4'b1111), .data_2(instr[19:16]), .sel(reg_src_a), .out(reg_addr_1));
    mux2 #(4) reg_addr2_mux(.data_1(instr[15:12]), .data_2(instr[3:0]), .sel(reg_src_b), .out(reg_addr_2));
    reg_file rf(.clk(clk), .reg_write_en(reg_write_en), .reg_addr_1(reg_addr_1), .reg_addr_2(reg_addr_2), .write_addr(instr[15:12]),
                .write_data(result), .reg_addr_15(pc_plus8), .read_data_1(src_a), .read_data_2(write_data));
    mux2 #(32) write_back_mux(.data_1(read_data), .data_2(alu_result), .sel(mem_to_reg), .out(result));



    // alu logic
    extend ext(.instr(instr[23:0]), .imm_src(imm_src), .ext_imm(ext_imm));
    mux2 #(32) alu_src_b(.data_1(ext_imm), .data_2(write_data), .sel(alu_src), .out(src_b));
    alu alu_i(.src_a(src_a), .src_b(src_b), .alu_control(alu_control), .zero(alu_flags[3]),
                .negative(alu_flags[2]), .overflow(alu_flags[1]), .carry(alu_flags[0]), .alu_result(alu_result));

endmodule

rtl/cond_decoder.v
module cond_decoder(input clk, reset, pc_s, reg_write, mem_write,
                    input [3:0] cond, alu_flags, flag_w,
                    output reg pc_src, reg_write_en, mem_write_en
                    );


    wire [3:0] flags;
    wire [3:0] flag_en;
    reg cond_ex;

    dff z_ff(.clk(clk), .reset(reset), .en(flag_en[3]), .d(alu_flags[3]), .q(flags[3]));
    dff n_ff(.clk(clk), .reset(reset), .en(flag_en[2]), .d(alu_flags[2]), .q(flags[2]));
    dff c_ff(.clk(clk), .reset(reset), .en(flag_en[1]), .d(alu_flags[1]), .q(flags[1]));
    dff v_ff(.clk(clk), .reset(reset), .en(flag_en[0]), .d(alu_flags[0]), .q(flags[0]));

    assign mem_write_en = cond_ex & mem_write;
    assign reg_write_en = cond_ex & reg_write;
    assign pc_src = cond_ex & pc_s;
    assign flag_en = flag_w & (4{cond_ex});

    cond_check cond_check_i (
        .cond(cond),
        .Z(flags[3]),
        .N(flags[2]),
        .C(flags[1]),
        .V(flags[0]),
        .cond_ex(cond_ex)
    );

endmodule




module cond_check(input [3:0] cond,
                  input Z, N, C, V
                  output reg cond_ex
                );

    always @(*)begin
        case(cond)
            4'b0000: cond_ex = Z;
            4'b0001: cond_ex = ~Z;
            4'b0010: cond_ex = C;
            4'b0011: cond_ex = ~C;
            4'b0100: cond_ex = N;
            4'b0101: cond_ex = ~N;
            4'b0110: cond_ex = V;
            4'b0111: cond_ex = ~V;
            4'b1000: cond_ex = C & ~Z;
            4'b1001: cond_ex = C | ~Z;
            4'b1010: cond_ex = (N == V);
            4'b1011: cond_ex = (N != V);
            4'b1100: cond_ex = ~Z & (N == V);
            4'b1101: cond_ex = Z | (N != V);
            4'b1110: cond_ex = 1'b1;
            default: cond_ex = 1'b0;
        endcase
    end


endmodule


module dff(
    input clk,
    input reset,
    input en,
    input d,
    output reg q
);

    always @(posedge clk or posedge reset) begin
        if (reset)
            q <= 1'b0;
        else if (en)
            q <= d;
    end

endmodule

rtl/decoder.v
module decoder(input [1:0] op,
                    input [5:0] funct,
                    input [3:0] rd,
                    output reg [3:0] flag_en,
                    output reg [2:0] alu_control,
                    output reg [1:0] imm_src,
                    output reg pc_s, reg_src_a, reg_src_b, mem_to_reg, alu_src,
                    output reg reg_write, mem_write
                    );

    reg alu_op, branch;
    reg [9:0] contr_sigs;


// main decoder
    always @(*) begin
        case(op)
            2'b00: if (funct[5]) contr_sigs = 10'b0001100010;
                    else contr_sigs = 10'b0000100010;
            2'b01: if (funct[0]) contr_sigs = 10'b0001010110;
                    else contr_sigs = 10'b0101000101;
            2'b10: contr_sigs = 10'b1011011000;
            default: contr_sigs = 10'b0;
        endcase
    
        {reg_src_a, reg_src_b, branch, alu_src, alu_op, mem_to_reg, imm_src, reg_write, mem_write} = contr_sigs;
    end



// Alu decoder
    always @(*) begin
        if (alu_op) begin
            case(funct[4:1])
                4'b0000: alu_control = 3'b000;
                4'b0001: alu_control = 3'b001;
                4'b0010: alu_control = 3'b010;
                4'b0011: alu_control = 3'b011;
                4'b0100: alu_control = 3'b100;
                default: alu_control = 3'b0;
            endcase
            flag_en[0] = funct[0] & (alu_control == 3'b010 | alu_control == 3'b011);
            flag_en[1] = funct[0] & (alu_control == 3'b010 | alu_control == 3'b011);
            flag_en[2] = funct[0];
            flag_en[3] = funct[0];
        end

        else begin
            alu_control = 3'b010;
            flag_en = 4'b0;
        end
    end


    always @(*) begin
        pc_s = ((rd == 4'b1111) & reg_write) | branch;
    end


endmodule

rtl/controller.v
module controller(input clk, reset, 
                  input [31:12] instr,
                  input [3:0] alu_flags,
                  output reg reg_write_en, mem_write_en, pc_src, reg_src_a, reg_src_b, mem_to_reg, alu_src,
                  output [2:0] alu_control, 
                  output [1:0] imm_src,
                );

    wire [3:0] flag_w;
    wire mem_write, reg_write, pc_s;

   decoder decoder_i(.op(instr[27:0]), .funct(instr[25:20]), .rd([15:12]),
                      .flag_en(flag_w), .alu_control(alu_control), .imm_src(imm_src)
                      .pc_s(pc_s), .reg_src_a(reg_src_a), .reg_src_b(reg_src_b),
                      .mem_to_reg(mem_to_reg), .alu_src(alu_src), .reg_write(reg_write)
                      .mem_write(mem_write) 
                      );


   cond_decoder cond_logic(.clk(clk), .reset(reset), .pc_s(pc_s), .reg_write(reg_write),
                            .mem_write(mem_write), .cond(instr[31:28]), .alu_flags(alu_flags),
                            .flag_w(flag_w), .pc_src(pc_src), .reg_write_en(reg_write_en), .mem_write_en(mem_write_en)
                            );

endmodule

rtl/cpu.v
module cpu(input clk, reset,
            output reg mem_write_en,
            input [31:0] instr, read_data, 
            output reg [31:0] write_data, write_addr, pc
            );


    wire reg_write_en, pc_src, reg_src_a, reg_src_b, mem_to_reg, alu_src;
    wire [3:0] alu_flags;
    wire [1:0] imm_src;
    wire [2:0] alu_control;


    controller controller_i(.clk(clk), .reset(reset), .instr(instr[31:12]), .alu_flags(alu_flags),
                            .reg_write_en(reg_write_en), .mem_write_en(mem_write_en), .pc_src(pc_src),
                            .reg_src_a(reg_src_a), .reg_src_b(reg_src_b), .mem_to_reg(mem_to_reg),
                            .alu_src(alu_src), .alu_control(alu_control), .imm_src(imm_src)
                            );


    datapath datapath_i(.clk(clk), .reset(reset),.reg_write_en(reg_write_en), .mem_write_en(mem_write_en), 
                        .pc_src(pc_src), .reg_src_a(reg_src_a), .reg_src_b(reg_src_b), .mem_to_reg(mem_to_reg),
                        .alu_src(alu_src), .alu_control(alu_control), .imm_src(imm_src), .write_data(write_data),
                        .alu_result(write_addr), .pc(pc), .read_data(read_data), .instr(instr), .alu_flags(alu_flags)
                        );


endmodule

tb/integration/tb_cpu.sv
`timescale 1ns/1ps

module cpu_tb;

    logic clk, reset, mem_write_en;
    logic [31:0] instr, read_data, write_data, result, pc;

    localparam CLK_PERIOD = 1;
     localparam TESTS_NO = 10;

    typedef struct packed {

        logic mem_write_en;
        logic [31:0] write_data; 
        logic [31:0] result;
        logic [31:0] pc;
    } outputs;
    
    outputs expected;
    


    cpu dut(.clk(clk),
            .reset(reset),
            .mem_write_en(mem_write_en),
            .instr(instr),
            .pc(pc),
            .write_addr(result),
            .write_data(write_data)
            );

    initial begin
                clk = 0;
                forever #CLK_PERIOD clk = ~clk;
    end

    // Reset Dut
    task automatic reset_dut;
        begin

            instr = 0;
            read_data = 0;
            reset = 1;
            @(posedge clk);
            reset = 0;

        end
    endtask

     // Driver - Apply inputs
    task automatic drive(input logic [31:0] instr_i,
                          input logic [31:0]  read_data_i);
        begin

            @(negedge clk);
            instr = instr_i;
            read_data = read_data_i;
        end
    endtask

    // checker
    task automatic check_outputs(input outputs out);

        begin

            @(posedge clk)
            assert ((out.pc === pc)) // program counter // 
                $display("[%0t] PASS", $time);
            else
                 $error("Expected pc=%0h Got=%0h", out.pc, pc);

            assert ((out.mem_write_en === mem_write_en)) // mem_write_en // 
                $display("[%0t] PASS", $time);
            else
                 $error("Expected mem_write_en=%0h Got=%0h", out.mem_write_en, mem_write_en);

            assert ((out.result === result)) //re
                $display("[%0t] PASS", $time);
            else
                 $error("Expected result=%0h Got=%0h", out.result, result); 

            assert ((out.write_data === write_data)) // write_data
                $display("[%0t] PASS", $time);
            else
                 $error("Expected write_data=%0h Got=%0h", out.write_data , write_data);
        end
    endtask


     // Test instruction cases 

    logic [31:0] instructions [TESTS_NO];
    logic [31:0] data [TESTS_NO];

    initial begin
        instructions[0] = 32'hE2A00019; // MOVI R0, #25;
        data[0] = 32'h0;
        instructions[1] = 32'hE2401005; // ADDI R1, #5  ; R1 = 30
        data[1] = 32'h0;
        instructions[2] = 32'hE0502001; // ADDS R2, R0 R1 ; R2 = 55
        data[2] = 32'h0;
        instructions[3] = 32'hE272304D;  // SUBIS R3, R2 #77; R3 = -22   
        data[3] = 32'h0;
        instructions[4] = 32'h42534016;  // ADDISNE R4, R3 #22 ; R4 = 0  
        data[4] = 32'h0;
        instructions[5] = 32'h00545000;  // ADDEQ R5, R4 R0 ; R5 = 25
        data[5] = 32'h0;
        instructions[6] = 32'hE0146005; // AND R6, R4 R5 ; R6 = 0
        data[6] = 32'h0; 


    end

// Reference model
    function automatic outputs ref_model(input logic [31:0] instr);

        outputs out;
        case(instr)

            32'hE2A00019: begin
                out.mem_write_en = 1'b0;
                out.pc = 32'h4;
                out.write_data = 32'hx;
                out.result = 32'h19;
            end 

            32'hE2401005: begin
                out.mem_write_en = 1'b0;
                out.pc = 32'h8;
                out.write_data = 32'hx;
                out.result = 32'h1E;
            end

            32'hE0502001: begin
                out.mem_write_en = 1'b0;
                out.pc = 32'hC;
                out.write_data = 32'h1E;
                out.result = 32'h37;
            end

            32'hE272304D: begin
                out.mem_write_en = 1'b0;
                out.pc = 32'h10;
                out.write_data = 32'hx;
                out.result = 32'hFFFFFFEA;
            end

            32'h42534016: begin
                out.mem_write_en = 1'b0;
                out.pc = 32'h14;
                out.write_data = 32'hx;
                out.result = 32'h0;
            end

            32'h00545000: begin
                out.mem_write_en = 1'b0;
                out.pc = 32'h18;
                out.write_data = 32'h19;
                out.result = 32'h19;
            end

            32'hE0146005: begin
                out.mem_write_en = 1'b0;
                out.pc = 32'h1C;
                out.write_data = 32'h19;
                out.result = 32'h0;
            end
        default: out = '0;
        endcase
    return out;

    endfunction

     initial begin

        $dumpfile("sim/waves/cpu.vcd");
        $dumpvars(0,  cpu_tb);

        reset_dut();
        $display("pc_content=%0h", pc);

        for (int i = 0; i < 7; i++)
        begin
            //$display("alu_srca=%0d... alu_srcb=%0d ... alu_result=%0d", dut.datapath_i.src_a, dut.datapath_i.src_b, dut.datapath_i.result);
            //$display("flags [ZNCV] = %0b%0b%0b%0b", dut.controller_i.cond_logic.z_ff.q, dut.controller_i.cond_logic.n_ff.q, dut.controller_i.cond_logic.c_ff.q, dut.controller_i.cond_logic.v_ff.q);
           //$display("reg_write_en = %0b", dut.reg_write_en);
            drive( instructions[i],  data[i]);
            $display("instruction code=%0h", instr);
            expected = ref_model(instructions[i]);
            check_outputs(expected);
        end

       //for(int i= 0; i < 5; i++)
        // $display("content of destination register[%0d]=%0d", i, dut.datapath_i.rf.reg_file[i]);


        $display("DONE");
        $finish;
    end

    
         

endmodule

sim/waves/cpu.vcd
$date
	Wed Jul 15 11:21:07 2026
$end
$version
	Icarus Verilog
$end
$timescale
	1ps
$end
$scope module cpu_tb $end
$var wire 32 ! write_data [31:0] $end
$var wire 32 " result [31:0] $end
$var wire 32 # pc [31:0] $end
$var wire 1 $ mem_write_en $end
$var parameter 32 % CLK_PERIOD $end
$var parameter 32 & TESTS_NO $end
$var reg 1 ' clk $end
$var reg 97 ( expected [96:0] $end
$var reg 32 ) instr [31:0] $end
$var reg 32 * read_data [31:0] $end
$var reg 1 + reset $end
$scope function ref_model $end
$upscope $end
$scope module dut $end
$var wire 1 ' clk $end
$var wire 32 , instr [31:0] $end
$var wire 32 - read_data [31:0] $end
$var wire 1 + reset $end
$var wire 32 . write_data [31:0] $end
$var wire 32 / write_addr [31:0] $end
$var wire 1 0 reg_write_en $end
$var wire 1 1 reg_src_b $end
$var wire 1 2 reg_src_a $end
$var wire 1 3 pc_src $end
$var wire 32 4 pc [31:0] $end
$var wire 1 $ mem_write_en $end
$var wire 1 5 mem_to_reg $end
$var wire 2 6 imm_src [1:0] $end
$var wire 1 7 alu_src $end
$var wire 4 8 alu_flags [3:0] $end
$var wire 3 9 alu_control [2:0] $end
$scope module controller_i $end
$var wire 1 ' clk $end
$var wire 20 : instr [31:12] $end
$var wire 1 + reset $end
$var wire 1 0 reg_write_en $end
$var wire 1 ; reg_write $end
$var wire 1 1 reg_src_b $end
$var wire 1 2 reg_src_a $end
$var wire 1 3 pc_src $end
$var wire 1 < pc_s $end
$var wire 1 $ mem_write_en $end
$var wire 1 = mem_write $end
$var wire 1 5 mem_to_reg $end
$var wire 2 > imm_src [1:0] $end
$var wire 4 ? flag_w [3:0] $end
$var wire 1 7 alu_src $end
$var wire 4 @ alu_flags [3:0] $end
$var wire 3 A alu_control [2:0] $end
$scope module cond_logic $end
$var wire 1 ' clk $end
$var wire 4 B cond [3:0] $end
$var wire 4 C flag_en [3:0] $end
$var wire 1 + reset $end
$var wire 1 ; reg_write $end
$var wire 1 < pc_s $end
$var wire 1 = mem_write $end
$var wire 4 D flags [3:0] $end
$var wire 4 E flag_w [3:0] $end
$var wire 1 F cond_ex $end
$var wire 4 G alu_flags [3:0] $end
$var reg 1 $ mem_write_en $end
$var reg 1 3 pc_src $end
$var reg 1 0 reg_write_en $end
$scope module c_ff $end
$var wire 1 ' clk $end
$var wire 1 H d $end
$var wire 1 I en $end
$var wire 1 + reset $end
$var reg 1 J q $end
$upscope $end
$scope module cond_check_i $end
$var wire 1 K C $end
$var wire 1 L N $end
$var wire 1 M V $end
$var wire 1 N Z $end
$var wire 4 O cond [3:0] $end
$var reg 1 F cond_ex $end
$upscope $end
$scope module n_ff $end
$var wire 1 ' clk $end
$var wire 1 P d $end
$var wire 1 Q en $end
$var wire 1 + reset $end
$var reg 1 R q $end
$upscope $end
$scope module v_ff $end
$var wire 1 ' clk $end
$var wire 1 S d $end
$var wire 1 T en $end
$var wire 1 + reset $end
$var reg 1 U q $end
$upscope $end
$scope module z_ff $end
$var wire 1 ' clk $end
$var wire 1 V d $end
$var wire 1 W en $end
$var wire 1 + reset $end
$var reg 1 X q $end
$upscope $end
$upscope $end
$scope module decoder_i $end
$var wire 6 Y funct [5:0] $end
$var wire 2 Z op [1:0] $end
$var wire 4 [ rd [3:0] $end
$var reg 3 \ alu_control [2:0] $end
$var reg 1 ] alu_op $end
$var reg 1 7 alu_src $end
$var reg 1 ^ branch $end
$var reg 10 _ contr_sigs [9:0] $end
$var reg 4 ` flag_en [3:0] $end
$var reg 2 a imm_src [1:0] $end
$var reg 1 5 mem_to_reg $end
$var reg 1 = mem_write $end
$var reg 1 < pc_s $end
$var reg 1 2 reg_src_a $end
$var reg 1 1 reg_src_b $end
$var reg 1 ; reg_write $end
$upscope $end
$upscope $end
$scope module datapath_i $end
$var wire 3 b alu_control [2:0] $end
$var wire 1 7 alu_src $end
$var wire 1 ' clk $end
$var wire 2 c imm_src [1:0] $end
$var wire 32 d instr [31:0] $end
$var wire 1 5 mem_to_reg $end
$var wire 1 $ mem_write_en $end
$var wire 1 3 pc_src $end
$var wire 32 e read_data [31:0] $end
$var wire 1 2 reg_src_a $end
$var wire 1 1 reg_src_b $end
$var wire 1 0 reg_write_en $end
$var wire 1 + reset $end
$var wire 32 f write_data [31:0] $end
$var wire 32 g src_b [31:0] $end
$var wire 32 h src_a [31:0] $end
$var wire 32 i result [31:0] $end
$var wire 4 j reg_addr_2 [3:0] $end
$var wire 4 k reg_addr_1 [3:0] $end
$var wire 32 l pc_plus8 [31:0] $end
$var wire 32 m pc_plus4 [31:0] $end
$var wire 32 n pc_next [31:0] $end
$var wire 32 o pc [31:0] $end
$var wire 32 p ext_imm [31:0] $end
$var wire 32 q alu_result [31:0] $end
$var wire 4 r alu_flags [3:0] $end
$scope module alu_i $end
$var wire 3 s alu_control [2:0] $end
$var wire 32 t src_b [31:0] $end
$var wire 32 u src_a [31:0] $end
$var reg 32 v alu_result [31:0] $end
$var reg 1 w carry $end
$var reg 1 x negative $end
$var reg 1 y overflow $end
$var reg 1 z zero $end
$upscope $end
$scope module alu_src_b $end
$var wire 1 7 sel $end
$var wire 32 { out [31:0] $end
$var wire 32 | data_2 [31:0] $end
$var wire 32 } data_1 [31:0] $end
$var parameter 32 ~ WIDTH $end
$upscope $end
$scope module ext $end
$var wire 2 !" imm_src [1:0] $end
$var wire 24 "" instr [23:0] $end
$var reg 32 #" ext_imm [31:0] $end
$upscope $end
$scope module pc_flops $end
$var wire 1 ' clk $end
$var wire 1 + reset $end
$var wire 32 $" data [31:0] $end
$var reg 32 %" q [31:0] $end
$upscope $end
$scope module pc_mux $end
$var wire 1 3 sel $end
$var wire 32 &" out [31:0] $end
$var wire 32 '" data_2 [31:0] $end
$var wire 32 (" data_1 [31:0] $end
$var parameter 32 )" WIDTH $end
$upscope $end
$scope module plus4_adder $end
$var wire 32 *" a [31:0] $end
$var wire 32 +" b [31:0] $end
$var wire 32 ," y [31:0] $end
$upscope $end
$scope module plus8_adder $end
$var wire 32 -" a [31:0] $end
$var wire 32 ." b [31:0] $end
$var wire 32 /" y [31:0] $end
$upscope $end
$scope module reg_addr1_mux $end
$var wire 4 0" data_1 [3:0] $end
$var wire 4 1" data_2 [3:0] $end
$var wire 1 2 sel $end
$var wire 4 2" out [3:0] $end
$var parameter 32 3" WIDTH $end
$upscope $end
$scope module reg_addr2_mux $end
$var wire 4 4" data_1 [3:0] $end
$var wire 4 5" data_2 [3:0] $end
$var wire 1 1 sel $end
$var wire 4 6" out [3:0] $end
$var parameter 32 7" WIDTH $end
$upscope $end
$scope module rf $end
$var wire 1 ' clk $end
$var wire 4 8" reg_addr_1 [3:0] $end
$var wire 32 9" reg_addr_15 [31:0] $end
$var wire 4 :" reg_addr_2 [3:0] $end
$var wire 1 0 reg_write_en $end
$var wire 4 ;" write_addr [3:0] $end
$var wire 32 <" write_data [31:0] $end
$var wire 32 =" read_data_2 [31:0] $end
$var wire 32 >" read_data_1 [31:0] $end
$upscope $end
$scope module write_back_mux $end
$var wire 32 ?" data_1 [31:0] $end
$var wire 32 @" data_2 [31:0] $end
$var wire 1 5 sel $end
$var wire 32 A" out [31:0] $end
$var parameter 32 B" WIDTH $end
$upscope $end
$upscope $end
$upscope $end
$scope begin $ivl_for_loop0 $end
$var integer 32 C" i [31:0] $end
$upscope $end
$scope task check_outputs $end
$upscope $end
$scope task drive $end
$upscope $end
$scope task reset_dut $end
$upscope $end
$upscope $end
$enddefinitions $end
$comment Show the parameter values. $end
$dumpall
b100000 B"
b100 7"
b100 3"
b100000 )"
b100000 ~
b1010 &
b1 %
$end
#0
$dumpvars
b0 C"
bx A"
bx @"
bz ?"
bx >"
bx ="
bx <"
b0 ;"
b0 :"
b1000 9"
b0 8"
b0 6"
b0 5"
b0 4"
b0 2"
b0 1"
b1111 0"
b1000 /"
b100 ."
b100 -"
b100 ,"
b100 +"
b0 *"
bx ("
b100 '"
b100 &"
b0 %"
b100 $"
b0 #"
b0 ""
b0 !"
b0 }
bx |
bx {
xz
0y
xx
0w
bx v
bx u
bx t
b0 s
bx00 r
bx q
b0 p
b0 o
b100 n
b100 m
b1000 l
b0 k
b0 j
bx i
bx h
bx g
bx f
bz e
b0 d
b0 c
b0 b
b0 a
b0 `
b100010 _
0^
1]
b0 \
b0 [
b0 Z
b0 Y
0X
0W
xV
0U
0T
0S
0R
0Q
xP
b0 O
0N
0M
0L
0K
0J
0I
0H
bx00 G
0F
b0 E
b0 D
b0 C
b0 B
b0 A
bx00 @
b0 ?
b0 >
0=
0<
1;
b0 :
b0 9
bx00 8
07
b0 6
05
b0 4
03
02
01
00
bx /
bx .
bz -
b0 ,
1+
b0 *
b0 )
bx (
0'
0$
b0 #
bx "
bx !
$end
#1000
b1000 n
b1000 $"
b1000 &"
b1100 l
b1100 /"
b1100 9"
b1000 m
b1000 '"
b1000 ,"
b1000 -"
b100 #
b100 4
b100 o
b100 %"
b100 *"
0+
1'
#2000
0P
0V
0x
b0 8
b0 @
b0 G
b0 r
0z
b11001 i
b11001 ("
b11001 <"
b11001 A"
b11001 "
b11001 /
b11001 q
b11001 v
b11001 @"
b11001 g
b11001 t
b11001 {
10
b101 9
b101 A
b101 \
b101 b
b101 s
17
b1100010 _
1F
b101010 Y
b1110 B
b1110 O
b1001 j
b1001 6"
b1001 :"
b11001 p
b11001 }
b11001 #"
b11100010101000000000 :
b1001 5"
b101000000000000000011001 ""
b0xxxxxxxxxxxxxxxxxxxxxxxxxxxxxxxx0000000000000000000000000001100100000000000000000000000000000100 (
b11100010101000000000000000011001 )
b11100010101000000000000000011001 ,
b11100010101000000000000000011001 d
0'
#3000
b1100 n
b1100 $"
b1100 &"
b11001 h
b11001 u
b11001 >"
b10000 l
b10000 /"
b10000 9"
b1100 m
b1100 '"
b1100 ,"
b1100 -"
b1000 #
b1000 4
b1000 o
b1000 %"
b1000 *"
b1 C"
1'
#4000
b11110 i
b11110 ("
b11110 <"
b11110 A"
b11110 "
b11110 /
b11110 q
b11110 v
b11110 @"
b10 9
b10 A
b10 \
b10 b
b10 s
b101 g
b101 t
b101 {
b100100 Y
b1 [
b101 j
b101 6"
b101 :"
b101 p
b101 }
b101 #"
b11100010010000000001 :
b1 4"
b101 5"
b1 ;"
b10000000001000000000101 ""
b0xxxxxxxxxxxxxxxxxxxxxxxxxxxxxxxx0000000000000000000000000001111000000000000000000000000000001000 (
b11100010010000000001000000000101 )
b11100010010000000001000000000101 ,
b11100010010000000001000000000101 d
0'
#5000
b10000 n
b10000 $"
b10000 &"
b10100 l
b10100 /"
b10100 9"
b10000 m
b10000 '"
b10000 ,"
b10000 -"
b1100 #
b1100 4
b1100 o
b1100 %"
b1100 *"
b10 C"
1'
#6000
1W
1Q
1I
1T
b110111 i
b110111 ("
b110111 <"
b110111 A"
b1111 C
b110111 "
b110111 /
b110111 q
b110111 v
b110111 @"
b1111 ?
b1111 E
b1111 `
07
b100010 _
b11110 !
b11110 .
b11110 f
b11110 |
b11110 ="
b11110 g
b11110 t
b11110 {
b101 Y
b10 [
b1 j
b1 6"
b1 :"
b1 p
b1 }
b1 #"
b11100000010100000010 :
b10 4"
b1 5"
b10 ;"
b10100000010000000000001 ""
b111100000000000000000000000000011011100000000000000000000000000001100 (
b11100000010100000010000000000001 )
b11100000010100000010000000000001 ,
b11100000010100000010000000000001 d
0'
#7000
b10100 n
b10100 $"
b10100 &"
b11000 l
b11000 /"
b11000 9"
b10100 m
b10100 '"
b10100 ,"
b10100 -"
b10000 #
b10000 4
b10000 o
b10000 %"
b10000 *"
b11 C"
1'
#8000
1P
1S
1x
b11111111111111111111111111101010 i
b11111111111111111111111111101010 ("
b11111111111111111111111111101010 <"
b11111111111111111111111111101010 A"
b101 8
b101 @
b101 G
b101 r
1w
b11111111111111111111111111101010 "
b11111111111111111111111111101010 /
b11111111111111111111111111101010 q
b11111111111111111111111111101010 v
b11111111111111111111111111101010 @"
b1001101 g
b1001101 t
b1001101 {
b11 9
b11 A
b11 \
b11 b
b11 s
17
b1100010 _
b110111 h
b110111 u
b110111 >"
bx !
bx .
bx f
bx |
bx ="
b100111 Y
b11 [
b10 k
b10 2"
b10 8"
b1101 j
b1101 6"
b1101 :"
b1001101 p
b1001101 }
b1001101 #"
b11100010011100100011 :
b10 1"
b11 4"
b1101 5"
b11 ;"
b11100100011000001001101 ""
b0xxxxxxxxxxxxxxxxxxxxxxxxxxxxxxxx1111111111111111111111111110101000000000000000000000000000010000 (
b11100010011100100011000001001101 )
b11100010011100100011000001001101 ,
b11100010011100100011000001001101 d
0'
#9000
b11000 n
b11000 $"
b11000 &"
1M
1L
b11100 l
b11100 /"
b11100 9"
b11000 m
b11000 '"
b11000 ,"
b11000 -"
b10100 #
b10100 4
b10100 o
b10100 %"
b10100 *"
1U
b101 D
1R
b100 C"
1'
#10000
0P
1V
0x
b1001 8
b1001 @
b1001 G
b1001 r
1z
b0 i
b0 ("
b0 <"
b0 A"
b0 "
b0 /
b0 q
b0 v
b0 @"
b10 9
b10 A
b10 \
b10 b
b10 s
b11111111111111111111111111101010 h
b11111111111111111111111111101010 u
b11111111111111111111111111101010 >"
b10110 g
b10110 t
b10110 {
b100101 Y
b100 [
b100 B
b100 O
b11 k
b11 2"
b11 8"
b110 j
b110 6"
b110 :"
b10110 p
b10110 }
b10110 #"
b1000010010100110100 :
b11 1"
b100 4"
b110 5"
b100 ;"
b10100110100000000010110 ""
b0xxxxxxxxxxxxxxxxxxxxxxxxxxxxxxxx0000000000000000000000000000000000000000000000000000000000010100 (
b1000010010100110100000000010110 )
b1000010010100110100000000010110 ,
b1000010010100110100000000010110 d
0'
#11000
0W
0Q
0I
0T
b0 C
00
0F
1N
0L
b11100 n
b11100 $"
b11100 &"
1X
b1001 D
0R
b100000 l
b100000 /"
b100000 9"
b11100 m
b11100 '"
b11100 ,"
b11100 -"
b11000 #
b11000 4
b11000 o
b11000 %"
b11000 *"
b101 C"
1'
#12000
0V
0z
b11001 i
b11001 ("
b11001 <"
b11001 A"
b11001 "
b11001 /
b11001 q
b11001 v
b11001 @"
1W
1Q
1I
1T
0S
b1111 C
10
b0 8
b0 @
b0 G
b0 r
0w
07
b100010 _
1F
b0 h
b0 u
b0 >"
b11001 !
b11001 .
b11001 f
b11001 |
b11001 ="
b11001 g
b11001 t
b11001 {
b101 Y
b101 [
b0 B
b0 O
b100 k
b100 2"
b100 8"
b0 j
b0 6"
b0 :"
b0 p
b0 }
b0 #"
b10101000101 :
b100 1"
b101 4"
b0 5"
b101 ;"
b10101000101000000000000 ""
b110010000000000000000000000000001100100000000000000000000000000011000 (
b10101000101000000000000 )
b10101000101000000000000 ,
b10101000101000000000000 d
0'
#13000
0W
0Q
0I
0T
b0 C
00
0F
b100000 n
b100000 $"
b100000 &"
0M
0N
b100100 l
b100100 /"
b100100 9"
b100000 m
b100000 '"
b100000 ,"
b100000 -"
b11100 #
b11100 4
b11100 o
b11100 %"
b11100 *"
0U
b0 D
0X
b110 C"
1'
