rtl/alu.v
module alu(input [31:0] src_a, src_b,
           input [2:0] alu_control,
           output reg zero, negative, overflow, carry,
           output reg[31:0] alu_result
        );


    always @(*) begin
        case(alu_control)
        3'b000: begin
            alu_result = src_a & src_b;
            carry = 0;
            overflow = 0;
        end
        3'b001:begin
           alu_result = src_a | src_b;
           carry = 0;
           overflow = 0; 
        end
        3'b010: begin
            {carry, alu_result} = src_a + src_b;
            overflow = ((src_a[31] == src_b[31]) && (alu_result[31] != src_a[31]));
        end

         3'b011: begin
            {carry, alu_result} = src_a - src_b;
            overflow = ((src_a[31] != src_b[31]) && (alu_result[31] != src_a[31]));

        end
        3'b100:begin
           alu_result = src_a ^ src_b;
           carry = 0;
           overflow = 0; 
        end
        3'b101: begin
            alu_result = src_b;
            carry = 0;
            overflow = 0;
        end
        default: begin
            alu_result = 32'b0;
            carry = 0;
            overflow = 0;

        end

        endcase
    end

   always @(*) begin
    zero = (alu_result == 0);
    negative = alu_result[31];
    end

endmodule

rtl/mux.v
module mux2 #(parameter WIDTH = 8) (
    input  [WIDTH-1:0] data_1, data_2,
    input sel,
    output [WIDTH-1:0] out
    );

    assign out = sel? data_1 : data_2;


endmodule

rtl/extend.v
module extend(input [23:0] instr, 
              input [1:0] imm_src,
              output reg [31:0] ext_imm
            );

  always @(*) begin
    case(imm_src)
      2'b00: ext_imm = {24'b0, instr[7:0]};
      2'b01: ext_imm = {20'b0, instr[11:0]};
      2'b10: ext_imm = {{8{instr[23]}}, instr[23:0]} << 2;
      default: ext_imm = 32'b0;
    endcase
  end

endmodule

rtl/register.v
module reg_file(input clk, reg_write_en, 
                input[3:0] reg_addr_1, reg_addr_2, write_addr,
                input[31:0] write_data, reg_addr_15,
                output [31:0] read_data_1, read_data_2
                );

    reg [31:0] reg_file[14:0];
    

    always @(posedge clk) begin
        if (reg_write_en) 
            reg_file[write_addr] <= write_data;
    end
            
    assign read_data_1 = (reg_addr_1 == 4'b1111) ? reg_addr_15 : reg_file[reg_addr_1];
    assign read_data_2 = (reg_addr_2 == 4'b1111) ? reg_addr_15 : reg_file[reg_addr_2];

endmodule

rtl/adder.v
module adder(input [31:0] a, b,
             output [31:0] y
             );

    assign y = a + b;


endmodule

rtl/pc.v
module pc(input clk, reset,
          input [31:0] data,
          output reg [31:0] q
          );

    always @(posedge clk or posedge reset) begin
        if (reset) 
            q <= 0;

        else
            q <= data;
    end

endmodule

rtl/datapath.v
module datapath(input clk, reset, reg_write_en, mem_write_en, pc_src, reg_src_a, reg_src_b, mem_to_reg, alu_src,
                input [2:0] alu_control, 
                input [1:0] imm_src,
                output [3:0] alu_flags,
                output [31:0] write_data, alu_result, pc,
                input [31:0] read_data, instr
                );


    wire [3:0] reg_addr_1, reg_addr_2;
    wire [31:0] pc_next, pc_plus4, pc_plus8;
    wire [31:0] ext_imm, src_a, src_b, result;

    // program counter logic
    mux2 #(32) pc_mux(.data_1(result), .data_2(pc_plus4), .sel(pc_src), .out(pc_next));
    pc pc_flops(.clk(clk), .reset(reset), .data(pc_next), .q(pc));
    adder plus4_adder(.a(pc), .b(32'b100), .y(pc_plus4));
    adder plus8_adder(.a(pc_plus4), .b(32'b100), .y(pc_plus8));


    // register file logc
    mux2 #(4) reg_addr1_mux(.data_1(4'b1111), .data_2(instr[19:16]), .sel(reg_src_a), .out(reg_addr_1));
    mux2 #(4) reg_addr2_mux(.data_1(instr[15:12]), .data_2(instr[3:0]), .sel(reg_src_b), .out(reg_addr_2));
    reg_file rf(.clk(clk), .reg_write_en(reg_write_en), .reg_addr_1(reg_addr_1), .reg_addr_2(reg_addr_2), .write_addr(instr[15:12]),
                .write_data(result), .reg_addr_15(pc_plus8), .read_data_1(src_a), .read_data_2(write_data));
    mux2 #(32) write_back_mux(.data_1(read_data), .data_2(alu_result), .sel(mem_to_reg), .out(result));



    // alu logic
    extend ext(.instr(instr[23:0]), .imm_src(imm_src), .ext_imm(ext_imm));
    mux2 #(32) alu_src_b(.data_1(ext_imm), .data_2(write_data), .sel(alu_src), .out(src_b));
    alu alu_i(.src_a(src_a), .src_b(src_b), .alu_control(alu_control), .zero(alu_flags[3]),
                .negative(alu_flags[2]), .overflow(alu_flags[1]), .carry(alu_flags[0]), .alu_result(alu_result));

endmodule

tb/integration/tb_datapath1.v
`timescale 1ns/1ps

module datapath_tb;

    reg clk, reset, pc_src, reg_write_en, reg_src_a, reg_src_b, alu_src;
    reg [2:0] alu_control;
    reg [31:0] instr;
    reg [1:0] imm_src;
    wire [3:0] alu_flags;
    wire [31:0] alu_result;

    datapath dut(
        .clk(clk),
        .reset(reset),
        .pc_src(pc_src),
        .reg_src_a(reg_src_a),
        .reg_src_b(reg_src_b),
        .alu_src(alu_src),
        .imm_src(imm_src),
        .alu_flags(alu_flags),
        .alu_control(alu_control),
        .instr(instr),
        .alu_result(alu_result)
    );


 // clock and reset
    initial begin
            clk = 0;
            reset = 1;
            #1;
            reset = 0;
        end

    // clock generator
    always #1 clk = ~clk;

    /* simulate and test Alu and its related logic */
    
      initial begin

        $dumpfile("sim/waves/datapath1.vcd");
        $dumpvars(0, datapath_tb);

        pc_src = 0;

        
        // temporary register file data
        dut.rf.reg_file[0] = 32'h0;
        dut.rf.reg_file[1] = 32'h1;
        dut.rf.reg_file[6] = 32'h6;
        dut.rf.reg_file[10] = 32'hA;
        dut.rf.reg_file[14] = 32'hE;


        // data processing opertaion
        instr = 32'h0006E00A; // Rs = 6, Rm = 10, Rd = 14
        alu_src = 0;
        reg_src_a = 0;
        reg_src_b = 0;
        alu_control = 3'b000;

        #0.1;
        if (alu_result != 32'h2) begin
            $error("wrong alu operation and result");
            $display("alu_result = %d", alu_result);
        end
        $display("alu_result = %d", alu_result);
        
        #1;
        alu_control = 3'b001;
        #0.1;
        if (alu_result != 32'hE) begin
            $error("wrong alu operation and result");
            $display("alu_result = %d", alu_result);
        end
        $display("alu_result = %h", alu_result);

        #1;

        // data processing, immediate operation

        instr = 32'h0006E0FF; // Rs = 6, Rm = 255, Rd = 14
        alu_src = 1;
        imm_src = 2'b00;
        alu_control = 3'b010;

        #0.1;

         if (alu_result != 32'h105) begin
            $error("wrong alu operation and result");
            $display("alu_result = %h", alu_result);
        end
        $display("alu_result = %h", alu_result);

        #1;

        /* mmory instruction */

        instr = 32'h0006EEFF;       // Rs = 6, Rm = EFF(3823), Rd = 14; 
        alu_src = 1;
        imm_src = 2'b01;
        alu_control = 3'b010;

         #0.1;

         if (alu_result != 32'hF05) begin
            $error("wrong alu operation and result");
            $display("alu_result = %h", alu_result);
        end
        $display("alu_result = %h", alu_result); // F05 (3845)

        #1;

        /* branch operartion instruction */

        instr = 32'h000000FF;       //branch to instruction no. 255
        reg_src_a = 1; // R15 = 16;
        alu_src = 1;
        imm_src = 2'b10;
        alu_control = 3'b010;

         #0.1;

         if (alu_result != 32'h40C) begin
            $error("wrong alu operation and result");
            $display("alu_result = %h", alu_result); // 40C (1036)
        end
        $display("alu_result = %h", alu_result); //  40C (1036)

         #1;


        $finish;

      end


endmodule

sim/waves/datapath1.vcd
$date
	Fri May 29 18:31:28 2026
$end
$version
	Icarus Verilog
$end
$timescale
	1ps
$end
$scope module datapath_tb $end
$var wire 32 ! alu_result [31:0] $end
$var wire 4 " alu_flags [3:0] $end
$var reg 3 # alu_control [2:0] $end
$var reg 1 $ alu_src $end
$var reg 1 % clk $end
$var reg 2 & imm_src [1:0] $end
$var reg 32 ' instr [31:0] $end
$var reg 1 ( pc_src $end
$var reg 1 ) reg_src_a $end
$var reg 1 * reg_src_b $end
$var reg 1 + reset $end
$scope module dut $end
$var wire 3 , alu_control [2:0] $end
$var wire 1 $ alu_src $end
$var wire 1 % clk $end
$var wire 2 - imm_src [1:0] $end
$var wire 32 . instr [31:0] $end
$var wire 1 / mem_to_reg $end
$var wire 1 0 mem_write_en $end
$var wire 1 ( pc_src $end
$var wire 32 1 read_data [31:0] $end
$var wire 1 ) reg_src_a $end
$var wire 1 * reg_src_b $end
$var wire 1 2 reg_write_en $end
$var wire 1 + reset $end
$var wire 32 3 write_data [31:0] $end
$var wire 32 4 src_b [31:0] $end
$var wire 32 5 src_a [31:0] $end
$var wire 32 6 result [31:0] $end
$var wire 4 7 reg_addr_2 [3:0] $end
$var wire 4 8 reg_addr_1 [3:0] $end
$var wire 32 9 pc_plus8 [31:0] $end
$var wire 32 : pc_plus4 [31:0] $end
$var wire 32 ; pc_next [31:0] $end
$var wire 32 < pc [31:0] $end
$var wire 32 = ext_imm [31:0] $end
$var wire 32 > alu_result [31:0] $end
$var wire 4 ? alu_flags [3:0] $end
$scope module alu_i $end
$var wire 3 @ alu_control [2:0] $end
$var wire 32 A src_b [31:0] $end
$var wire 32 B src_a [31:0] $end
$var reg 32 C alu_result [31:0] $end
$var reg 1 D carry $end
$var reg 1 E negative $end
$var reg 1 F overflow $end
$var reg 1 G zero $end
$upscope $end
$scope module alu_src_b $end
$var wire 1 $ sel $end
$var wire 32 H out [31:0] $end
$var wire 32 I data_2 [31:0] $end
$var wire 32 J data_1 [31:0] $end
$var parameter 32 K WIDTH $end
$upscope $end
$scope module ext $end
$var wire 2 L imm_src [1:0] $end
$var wire 24 M instr [23:0] $end
$var reg 32 N ext_imm [31:0] $end
$upscope $end
$scope module pc_flops $end
$var wire 1 % clk $end
$var wire 1 + reset $end
$var wire 32 O data [31:0] $end
$var reg 32 P q [31:0] $end
$upscope $end
$scope module pc_mux $end
$var wire 1 ( sel $end
$var wire 32 Q out [31:0] $end
$var wire 32 R data_2 [31:0] $end
$var wire 32 S data_1 [31:0] $end
$var parameter 32 T WIDTH $end
$upscope $end
$scope module plus4_adder $end
$var wire 32 U a [31:0] $end
$var wire 32 V b [31:0] $end
$var wire 32 W y [31:0] $end
$upscope $end
$scope module plus8_adder $end
$var wire 32 X a [31:0] $end
$var wire 32 Y b [31:0] $end
$var wire 32 Z y [31:0] $end
$upscope $end
$scope module reg_addr1_mux $end
$var wire 4 [ data_1 [3:0] $end
$var wire 4 \ data_2 [3:0] $end
$var wire 1 ) sel $end
$var wire 4 ] out [3:0] $end
$var parameter 32 ^ WIDTH $end
$upscope $end
$scope module reg_addr2_mux $end
$var wire 4 _ data_1 [3:0] $end
$var wire 4 ` data_2 [3:0] $end
$var wire 1 * sel $end
$var wire 4 a out [3:0] $end
$var parameter 32 b WIDTH $end
$upscope $end
$scope module rf $end
$var wire 1 % clk $end
$var wire 4 c reg_addr_1 [3:0] $end
$var wire 32 d reg_addr_15 [31:0] $end
$var wire 4 e reg_addr_2 [3:0] $end
$var wire 1 2 reg_write_en $end
$var wire 4 f write_addr [3:0] $end
$var wire 32 g write_data [31:0] $end
$var wire 32 h read_data_2 [31:0] $end
$var wire 32 i read_data_1 [31:0] $end
$upscope $end
$scope module write_back_mux $end
$var wire 32 j data_1 [31:0] $end
$var wire 32 k data_2 [31:0] $end
$var wire 1 / sel $end
$var wire 32 l out [31:0] $end
$var parameter 32 m WIDTH $end
$upscope $end
$upscope $end
$upscope $end
$enddefinitions $end
$comment Show the parameter values. $end
$dumpall
b100000 m
b100 b
b100 ^
b100000 T
b100000 K
$end
#0
$dumpvars
bx l
b10 k
bz j
b110 i
b1010 h
bx g
b1110 f
b1010 e
b1000 d
b110 c
b1010 a
b1010 `
b1110 _
b110 ]
b110 \
b1111 [
b1000 Z
b100 Y
b100 X
b100 W
b100 V
b0 U
bx S
b100 R
b100 Q
b0 P
b100 O
b0 N
b1101110000000001010 M
bx L
b0 J
b1010 I
b1010 H
0G
0F
0E
0D
b10 C
b110 B
b1010 A
b0 @
b0 ?
b10 >
b0 =
b0 <
b100 ;
b100 :
b1000 9
b110 8
b1010 7
bx 6
b110 5
b1010 4
b1010 3
z2
bz 1
z0
z/
b1101110000000001010 .
bx -
b0 ,
1+
0*
0)
0(
b1101110000000001010 '
bx &
0%
0$
b0 #
b0 "
b10 !
$end
#1000
b1000 ;
b1000 O
b1000 Q
b1100 9
b1100 Z
b1100 d
b1000 :
b1000 R
b1000 W
b1000 X
b100 <
b100 P
b100 U
1%
0+
#1100
b1110 !
b1110 >
b1110 C
b1110 k
b1 #
b1 ,
b1 @
#2000
0%
#2200
b1100 3
b1100 I
b1100 h
b1111 7
b1111 a
b1111 e
b100000101 !
b100000101 >
b100000101 C
b100000101 k
b11111111 =
b11111111 J
b11111111 N
b11111111 4
b11111111 A
b11111111 H
b1111 `
b1101110000011111111 M
b10 #
b10 ,
b10 @
b0 &
b0 -
b0 L
1$
b1101110000011111111 '
b1101110000011111111 .
#3000
b10000 3
b10000 I
b10000 h
b1100 ;
b1100 O
b1100 Q
b10000 9
b10000 Z
b10000 d
b1100 :
b1100 R
b1100 W
b1100 X
b1000 <
b1000 P
b1000 U
1%
#3300
b111100000101 !
b111100000101 >
b111100000101 C
b111100000101 k
b111011111111 4
b111011111111 A
b111011111111 H
b111011111111 =
b111011111111 J
b111011111111 N
b1101110111011111111 M
b1 &
b1 -
b1 L
b1101110111011111111 '
b1101110111011111111 .
#4000
0%
#4400
b10000001100 !
b10000001100 >
b10000001100 C
b10000001100 k
b1111111100 4
b1111111100 A
b1111111100 H
b10000 5
b10000 B
b10000 i
b1111111100 =
b1111111100 J
b1111111100 N
b1111 8
b1111 ]
b1111 c
b0 \
b0 _
b0 f
b11111111 M
b10 &
b10 -
b10 L
1)
b11111111 '
b11111111 .
#5000
b10000010000 !
b10000010000 >
b10000010000 C
b10000010000 k
b10100 5
b10100 B
b10100 i
b10100 3
b10100 I
b10100 h
b10000 ;
b10000 O
b10000 Q
b10100 9
b10100 Z
b10100 d
b10000 :
b10000 R
b10000 W
b10000 X
b1100 <
b1100 P
b1100 U
1%
