rtl/data_mem.v
module data_mem(input clk, mem_write_en, 
                input [31:0] addr, write_data,
                output [31:0] read_data
                );

    reg [31:0] RAM[31:0];
    assign read_data = RAM[addr[31:2]];

    always @(posedge clk) begin
        if (mem_write_en) 
             RAM[addr[31:2]] <= write_data;
    end


endmodule

tb/units/tb_data_mem.sv
`timescale 1ns/1ps

module data_mem_tb;
    logic clk, mem_write_en;
    logic [31:0] addr, write_data, read_data;

    localparam CLK_PERIOD = 1;

    logic [31:0] expected_ram[0:31];
    logic [31:0] expected;

    data_mem uut(.clk(clk),
                 .mem_write_en(mem_write_en),
                 .addr(addr),
                 .write_data(write_data),
                 .read_data(read_data)
                );

    initial begin
            clk = 0;
            forever #CLK_PERIOD clk = ~clk;
    end

    task automatic drive_write(input logic mem_write_en_i,
                               input logic [31:0] addr_i,
                               input logic [31:0] write_data_i
                                );
        begin
           @(negedge clk);
            mem_write_en = mem_write_en_i;
            addr = addr_i;
            write_data = write_data_i;
        end
    endtask

    task automatic drive_addr(input logic [31:0] addr_i);
        @(negedge clk)
         addr = addr_i;
    endtask

    function automatic logic [31:0] drive_read(input logic [31:0] addr_i);

        logic [31:0] expected_data;
         expected_data = expected_ram[addr_i >> 2];
        return expected_data;

    endfunction

    task automatic check_data(input logic [31:0] expected_data);

        assert((read_data === expected_data))
             $display("[%0t] PASS", $time);
        else
            $error("Expected expected_data=%0d Got=%0d", expected_data, read_data);
    endtask


    // generete random data and addresses
    logic [31:0] addresses[5], write_datas[5];


    initial begin

        addresses[0] = $urandom_range(31) << 2;
        addresses[1] = $urandom_range(31) << 2;
        addresses[2] = $urandom_range(31) << 2;
        addresses[3] = $urandom_range(31) << 2;
        addresses[4] = $urandom_range(31) << 2;

       
        write_datas[0] = $urandom();
        write_datas[1] = $urandom();
        write_datas[2] = $urandom();
        write_datas[3] = $urandom();
        write_datas[4] = $urandom();

        uut.RAM[addresses[0] >> 2] = write_datas[0];
        uut.RAM[addresses[1] >> 2] = write_datas[1];
        uut.RAM[addresses[2] >> 2] = write_datas[2];
        uut.RAM[addresses[3] >> 2] = write_datas[3];
        uut.RAM[addresses[4] >> 2] = write_datas[4];

    end

    initial begin
        $dumpfile("sim/waves/data_mem.vcd");
        $dumpvars(0,  data_mem_tb);
       

        for (int i = 0; i < 5; i++)  // write data into adresssed location
        begin
            drive_write(1'b1,
                        addresses[i],
                        write_datas[i]
                        );

            @(posedge clk);
            if(mem_write_en)
                expected_ram[addr >> 2] = write_data;
        end

        // mem_write_enable = 0;
        drive_write(1'b0,
                    addresses[3],
                    32'hFFFFF
                        );
         @(posedge clk);
          if(mem_write_en)
            expected_ram[(addr >> 2)] <= write_data;
         expected = drive_read(addresses[3]);
         check_data(expected);

         // check read operation

          for (int i = 0; i < 5; i++)
          begin
            drive_addr(addresses[i]);
            @(posedge clk);
            expected = drive_read(addresses[i]);
            check_data(expected);
          end


        $display("DONE");
        $finish;
    end


endmodule

sim/waves/data_mem.vcd
$date
	Thu Jul  9 16:33:27 2026
$end
$version
	Icarus Verilog
$end
$timescale
	1ps
$end
$scope module data_mem_tb $end
$var wire 32 ! read_data [31:0] $end
$var parameter 32 " CLK_PERIOD $end
$var reg 32 # addr [31:0] $end
$var reg 1 $ clk $end
$var reg 32 % expected [31:0] $end
$var reg 1 & mem_write_en $end
$var reg 32 ' write_data [31:0] $end
$scope function drive_read $end
$upscope $end
$scope module uut $end
$var wire 32 ( addr [31:0] $end
$var wire 1 $ clk $end
$var wire 1 & mem_write_en $end
$var wire 32 ) write_data [31:0] $end
$var reg 32 * read_data [31:0] $end
$upscope $end
$scope begin $ivl_for_loop0 $end
$var integer 32 + i [31:0] $end
$upscope $end
$scope begin $ivl_for_loop1 $end
$var integer 32 , i [31:0] $end
$upscope $end
$scope task check_data $end
$upscope $end
$scope task drive_addr $end
$upscope $end
$scope task drive_write $end
$upscope $end
$upscope $end
$enddefinitions $end
$comment Show the parameter values. $end
$dumpall
b1 "
$end
#0
$dumpvars
b0 ,
b0 +
bx *
bx )
bx (
bx '
x&
bx %
0$
bx #
bx !
$end
#1000
1$
#2000
b11000110110111111001100110001101 !
b11000110110111111001100110001101 *
b11000110110111111001100110001101 '
b11000110110111111001100110001101 )
b1001000 #
b1001000 (
1&
0$
#3000
b1 +
1$
#4000
b110010110000101000010001100101 !
b110010110000101000010001100101 *
b110010110000101000010001100101 '
b110010110000101000010001100101 )
b100000 #
b100000 (
0$
#5000
b10 +
1$
#6000
b1001001101110101001000010010 !
b1001001101110101001000010010 *
b1001001101110101001000010010 '
b1001001101110101001000010010 )
b0 #
b0 (
0$
#7000
b11 +
1$
#8000
b10000000111100111110001100000001 !
b10000000111100111110001100000001 *
b10000000111100111110001100000001 '
b10000000111100111110001100000001 )
b11000 #
b11000 (
0$
#9000
b100 +
1$
#10000
b10000110110101111100110100001101 !
b10000110110101111100110100001101 *
b10000110110101111100110100001101 '
b10000110110101111100110100001101 )
b1000000 #
b1000000 (
0$
#11000
b101 +
1$
#12000
b10000000111100111110001100000001 !
b10000000111100111110001100000001 *
b11111111111111111111 '
b11111111111111111111 )
b11000 #
b11000 (
0&
0$
#13000
b10000000111100111110001100000001 %
1$
#14000
b11000110110111111001100110001101 !
b11000110110111111001100110001101 *
b1001000 #
b1001000 (
0$
#15000
b1 ,
b11000110110111111001100110001101 %
1$
#16000
b110010110000101000010001100101 !
b110010110000101000010001100101 *
b100000 #
b100000 (
0$
#17000
b10 ,
b110010110000101000010001100101 %
1$
#18000
b1001001101110101001000010010 !
b1001001101110101001000010010 *
b0 #
b0 (
0$
#19000
b11 ,
b1001001101110101001000010010 %
1$
#20000
b10000000111100111110001100000001 !
b10000000111100111110001100000001 *
b11000 #
b11000 (
0$
#21000
b100 ,
b10000000111100111110001100000001 %
1$
#22000
b10000110110101111100110100001101 !
b10000110110101111100110100001101 *
b1000000 #
b1000000 (
0$
#23000
b101 ,
b10000110110101111100110100001101 %
1$
