rtl/decoder.v
module decoder(input [1:0] op,
                    input [5:0] funct,
                    input [3:0] rd,
                    output reg [3:0] flag_en,
                    output reg [2:0] alu_control,
                    output reg [1:0] imm_src,
                    output reg pc_s, reg_src_a, reg_src_b, mem_to_reg, alu_src,
                    output reg reg_write, mem_write
                    );

    reg alu_op, branch;
    reg [9:0] contr_sigs;


// main decoder
    always @(*) begin
        case(op)
            2'b00: if (funct[5]) contr_sigs = 10'b0001100010;
                    else contr_sigs = 10'b0000100010;
            2'b01: if (funct[0]) contr_sigs = 10'b0001010110;
                    else contr_sigs = 10'b0101000101;
            2'b10: contr_sigs = 10'b1011011000;
            default: contr_sigs = 10'b0;
        endcase
    
        {reg_src_a, reg_src_b, branch, alu_src, alu_op, mem_to_reg, imm_src, reg_write, mem_write} = contr_sigs;
    end



// Alu decoder
    always @(*) begin
        if (alu_op) begin
            case(funct[4:1])
                4'b0000: alu_control = 3'b000;
                4'b0001: alu_control = 3'b001;
                4'b0010: alu_control = 3'b010;
                4'b0011: alu_control = 3'b011;
                4'b0100: alu_control = 3'b100;
                default: alu_control = 3'b0;
            endcase
            flag_en[0] = funct[0] & (alu_control == 3'b010 | alu_control == 3'b011);
            flag_en[1] = funct[0] & (alu_control == 3'b010 | alu_control == 3'b011);
            flag_en[2] = funct[0];
            flag_en[3] = funct[0];
        end

        else begin
            alu_control = 3'b010;
            flag_en = 4'b0;
        end
    end


    always @(*) begin
        pc_s = ((rd == 4'b1111) & reg_write) | branch;
    end


endmodule

tb/units/tb_decoder.sv
`timescale 1ns/1ps

module decoder_tb;


    logic [5:0] funct;
    logic [1:0] op;
    logic [3:0] rd;
    logic pc_s, reg_src_a, reg_src_b, mem_to_reg, alu_src, reg_write, mem_write;
    logic [1:0] imm_src;
    logic [2:0] alu_control;
    logic [3:0] flag_en;

    decoder uut(.op(op),
                .funct(funct),
                .rd(rd),
                .pc_s(pc_s),
                .reg_src_a(reg_src_a),
                .reg_src_b(reg_src_b),
                .mem_to_reg(mem_to_reg),
                .alu_src(alu_src),
                .reg_write(reg_write),
                .mem_write(mem_write),
                .imm_src(imm_src),
                .alu_control(alu_control),
                .flag_en(flag_en)
                );


    initial begin
        $dumpfile("sim/waves/decoder.vcd");
        $dumpvars(0, decoder_tb);

        op = 2'b00;
        funct = 0;
        #1;
        assert (!reg_src_a && !reg_src_b && !uut.branch && !alu_src && 
                uut.alu_op && !mem_to_reg && reg_write && !mem_write)
            $display("expected control signal for data processing operation (register)");
        else
            $error("invalid control output");

        assert ({reg_src_a, reg_src_b, uut.branch, alu_src, uut.alu_op,
                mem_to_reg, imm_src, reg_write, mem_write} ==  10'b0000100010)
            $display("expected control signal for data processing operation (register)");
        else
            $error("invalid control output");
        $display("control output for register data processing = %b", uut.contr_sigs);


        #1;
        // immediate data processing operation
        funct = 6'b100000;
        #0.1;
        assert (!reg_src_a && !reg_src_b && !uut.branch && alu_src && uut.alu_op && 
                !mem_to_reg && (imm_src == 2'b00) && reg_write && !mem_write)
            $display("expected control signal for data processing operation (immediate)");
        else
            $error("invalid data processing (immediate) control output");

        assert ({reg_src_a, reg_src_b, uut.branch, alu_src, uut.alu_op,
                mem_to_reg, imm_src, reg_write, mem_write} ==  10'b0001100010)
            $display("expected control signal for data processing operation (immediate)");
        else
            $error("invalid data processing (immediate) control output");
         $display("control output for immediate data processing = %b", uut.contr_sigs);

        #1;
         // memory operation
        op = 2'b01;
        funct = 0;
        #0.1;

        assert (!reg_src_a && reg_src_b && !uut.branch && alu_src && !uut.alu_op && 
                !mem_to_reg && (imm_src == 2'b01) && !reg_write && mem_write)
            $display("expected control signal for 'store' memory operation");
        else
            $error("invalid store operation control output");
        $display("control output for 'store' memory operation = %b", uut.contr_sigs);

        #1;
        funct = 1;
        #0.1;

         assert (!reg_src_a && !reg_src_b && !uut.branch && alu_src && !uut.alu_op && 
                mem_to_reg && (imm_src == 2'b01) && reg_write && !mem_write)
            $display("expected control signal for 'load' memory operation");
        else
            $error("invalid load operation control output");
        $display("control output for 'load' memory operation = %b", uut.contr_sigs);

        #1;

        // branch operation
        op = 2'b10;
        #0.1;

        assert (reg_src_a && !reg_src_b && uut.branch && alu_src && !uut.alu_op && 
                mem_to_reg && (imm_src == 2'b10) && !reg_write && !mem_write)
            $display("expected control signal for branch operation");
        else
            $error("invalid branch operation control output");
        $display("control output for branch operation = %b", uut.contr_sigs);



        // alu control and set flags
        #1;
        force uut.alu_op = 0;
        #0.1;

        assert ((alu_control == 3'b010) && (flag_en == 4'b0))
            $display("expected alu operation verified");
        else
            $error("unexpected alu operation");
            

        
        #1;
        force uut.alu_op = 1;
        funct = 6'b000101;
        op = 2'b00; //  flag_en = 4'b111
        
        #0.1;
        assert ((flag_en == 4'b1111) && (alu_control == 3'b010))
            $display("ALU operation and status flag set verified");
        else
            $error("worng ALU operation and unexpected flags set");

        #1;
        funct = 6'b000001; // AND Operation flag_en = 4'b1100
        
        #0.1;
        assert ((flag_en == 4'b1100) && (alu_control == 3'b000))
            $display("ALU operation and status flag set verified");
        else
            $error("worng ALU operation and unexpected flags set");

            #1;

        funct = 6'b000011; // OR Operation  flag_en = 4'b1100
        
        #0.1;
        assert ((flag_en == 4'b1100) && (alu_control == 3'b001))
            $display("ALU operation and status flag set verified");
        else
            $error("worng ALU operation and unexpected flags set");

        #1;

        funct = 6'b000111; // SUB Operation  flag_en = 4'b1111
            
        #0.1;
        assert ((flag_en == 4'b1111) && (alu_control == 3'b011))
            $display("ALU operation and status flag set verified");
        else
            $error("worng ALU operation and unexpected flags set");

        #1;

        funct = 6'b001001; // SUB Operation  flag_en = 4'b1111

        #0.1;
        assert ((flag_en == 4'b1100) && (alu_control == 3'b100))
            $display("ALU operation and status flag set verified");
        else
            $error("worng ALU operation and unexpected flags set");

        release uut.alu_op;


        #1;
        // branch operation control
        rd = 4'b1110;
        force uut.branch = 0;

        #0.1;
        assert (!pc_s)
            $display("expected program counter mux selector value");
        else
            $error("wrong pc sel value");
            
        #1;


        rd = 4'b1111;
        op = 2'b00;
        #0.1;
        assert (pc_s)
            $display("correct program counter mux selector value!");
        else
            $error("wrong pc sel value");

         #1;

        force uut.branch = 0;

        #0.1;
        assert (pc_s)
            $display("correct program counter mux selector value!");
        else
            $error("wrong pc sel value");

        #1;

        force uut.branch = 0;
        rd = 4'b1111;

        #0.1;
        assert (pc_s)
            $display("correct program counter mux selector value!");
        else
            $error("wrong pc sel value");



        $finish;
        
    end

endmodule

sim/waves/decoder.vcd
$date
	Sun Jun  7 22:20:35 2026
$end
$version
	Icarus Verilog
$end
$timescale
	1ps
$end
$scope module decoder_tb $end
$var wire 1 ! reg_write $end
$var wire 1 " reg_src_b $end
$var wire 1 # reg_src_a $end
$var wire 1 $ pc_s $end
$var wire 1 % mem_write $end
$var wire 1 & mem_to_reg $end
$var wire 2 ' imm_src [1:0] $end
$var wire 4 ( flag_en [3:0] $end
$var wire 1 ) alu_src $end
$var wire 3 * alu_control [2:0] $end
$var reg 6 + funct [5:0] $end
$var reg 2 , op [1:0] $end
$var reg 4 - rd [3:0] $end
$scope module uut $end
$var wire 6 . funct [5:0] $end
$var wire 2 / op [1:0] $end
$var wire 4 0 rd [3:0] $end
$var reg 3 1 alu_control [2:0] $end
$var reg 1 2 alu_op $end
$var reg 1 ) alu_src $end
$var reg 1 3 branch $end
$var reg 10 4 contr_sigs [9:0] $end
$var reg 4 5 flag_en [3:0] $end
$var reg 2 6 imm_src [1:0] $end
$var reg 1 & mem_to_reg $end
$var reg 1 % mem_write $end
$var reg 1 $ pc_s $end
$var reg 1 # reg_src_a $end
$var reg 1 " reg_src_b $end
$var reg 1 ! reg_write $end
$upscope $end
$upscope $end
$enddefinitions $end
$comment Show the parameter values. $end
$dumpall
$end
#0
$dumpvars
b0 6
b0 5
b100010 4
03
12
b0 1
bx 0
b0 /
b0 .
bx -
b0 ,
b0 +
b0 *
0)
b0 (
b0 '
0&
0%
x$
0#
0"
1!
$end
#2000
1)
b1100010 4
b100000 +
b100000 .
#3100
0$
b10 *
b10 1
1"
02
b1 '
b1 6
0!
1%
b101000101 4
b0 +
b0 .
b1 ,
b1 /
#4200
x$
0"
1&
1!
0%
b1010110 4
b1 +
b1 .
#5300
1$
1#
13
b10 '
b10 6
0!
b1011011000 4
b10 ,
b10 /
#6400
02
#7500
x$
0#
03
0)
0&
b0 '
b0 6
1!
b100010 4
b1111 (
b1111 5
b0 ,
b0 /
b101 +
b101 .
12
#8600
b1100 (
b1100 5
b0 *
b0 1
b1 +
b1 .
#9700
b1 *
b1 1
b11 +
b11 .
#10800
b1111 (
b1111 5
b11 *
b11 1
b111 +
b111 .
#11900
b1100 (
b1100 5
b100 *
b100 1
b1001 +
b1001 .
#13000
0$
03
b1110 -
b1110 0
#14100
1$
b1111 -
b1111 0
#15200
03
#16300
03
