rtl/cond_decoder.v
module cond_decoder(input clk, reset, pc_s, reg_write, mem_write,
                    input [3:0] cond, alu_flags, flag_w,
                    output reg pc_src, reg_write_en, mem_write_en
                    );


    wire [3:0] flags;
    wire [3:0] flag_en;
    reg cond_ex;

    dff z_ff(.clk(clk), .reset(reset), .en(flag_en[3]), .d(alu_flags[3]), .q(flags[3]));
    dff n_ff(.clk(clk), .reset(reset), .en(flag_en[2]), .d(alu_flags[2]), .q(flags[2]));
    dff c_ff(.clk(clk), .reset(reset), .en(flag_en[1]), .d(alu_flags[1]), .q(flags[1]));
    dff v_ff(.clk(clk), .reset(reset), .en(flag_en[0]), .d(alu_flags[0]), .q(flags[0]));

    assign mem_write_en = cond_ex & mem_write;
    assign reg_write_en = cond_ex & reg_write;
    assign pc_src = cond_ex & pc_s;
    assign flag_en = flag_w & (4{cond_ex});

    cond_check cond_check_i (
        .cond(cond),
        .Z(flags[3]),
        .N(flags[2]),
        .C(flags[1]),
        .V(flags[0]),
        .cond_ex(cond_ex)
    );

endmodule




module cond_check(input [3:0] cond,
                  input Z, N, C, V
                  output reg cond_ex
                );

    always @(*)begin
        case(cond)
            4'b0000: cond_ex = Z;
            4'b0001: cond_ex = ~Z;
            4'b0010: cond_ex = C;
            4'b0011: cond_ex = ~C;
            4'b0100: cond_ex = N;
            4'b0101: cond_ex = ~N;
            4'b0110: cond_ex = V;
            4'b0111: cond_ex = ~V;
            4'b1000: cond_ex = C & ~Z;
            4'b1001: cond_ex = C | ~Z;
            4'b1010: cond_ex = (N == V);
            4'b1011: cond_ex = (N != V);
            4'b1100: cond_ex = ~Z & (N == V);
            4'b1101: cond_ex = Z | (N != V);
            4'b1110: cond_ex = 1'b1;
            default: cond_ex = 1'b0;
        endcase
    end


endmodule


module dff(
    input clk,
    input reset,
    input en,
    input d,
    output reg q
);

    always @(posedge clk or posedge reset) begin
        if (reset)
            q <= 1'b0;
        else if (en)
            q <= d;
    end

endmodule

tb/units/tb_dff.sv
`timescale 1ns/1ps

module dff_tb;

    logic clk, reset, en;
    logic d, q;

    localparam CLK_PERIOD = 1;


    dff uut(.clk(clk), .reset(reset), .en(en), .d(d), .q(q));

    initial begin
        clk = 0;
        forever #CLK_PERIOD clk = ~clk;
    end


    task initialize;
        begin
            reset = 0;
            d = 0;
            en = 0;
        end
    endtask

    task drive(input logic en_i,
            input logic data);

        begin

            @(negedge clk);
            en = en_i;
            d = data;
        end
    endtask

    task check(input logic expected);
        begin
             @(posedge clk);
            if (q !== expected)
                $error("Expected=%0b Got=%0b", expected, q);
            else
                $display("[%0t] PASS", $time);
        end
    endtask



    initial begin
        $dumpfile("sim/waves/dff.vcd");
        $dumpvars(0, dff_tb);
       
        initialize();

        // Reset
        reset = 1;
        repeat(2) @(posedge clk);
        reset = 0;

        
        drive(1, 1);
        @(posedge clk);
        check(1);

        // enable signal off
        drive(0, 0);
        @(posedge clk);
        check(1);

        // enable signal on
        drive(1, 0);
        @(posedge clk);
        check(0);

        $finish;

    end


endmodule

sim/waves/dff.vcd
$date
	Thu Jul  2 06:49:33 2026
$end
$version
	Icarus Verilog
$end
$timescale
	1ps
$end
$scope module dff_tb $end
$var wire 1 ! q $end
$var parameter 32 " CLK_PERIOD $end
$var reg 1 # clk $end
$var reg 1 $ d $end
$var reg 1 % en $end
$var reg 1 & reset $end
$scope module uut $end
$var wire 1 # clk $end
$var wire 1 $ d $end
$var wire 1 % en $end
$var wire 1 & reset $end
$var reg 1 ! q $end
$upscope $end
$scope task check $end
$var reg 1 ' expected $end
$upscope $end
$scope task drive $end
$var reg 1 ( data $end
$var reg 1 ) en_i $end
$upscope $end
$scope task initialize $end
$upscope $end
$upscope $end
$enddefinitions $end
$comment Show the parameter values. $end
$dumpall
b1 "
$end
#0
$dumpvars
x)
x(
x'
1&
0%
0$
0#
0!
$end
#1000
1#
#2000
0#
#3000
1(
1)
0&
1#
#4000
1$
1%
0#
#5000
1!
1'
1#
#6000
0#
#7000
0(
0)
1#
#8000
0$
0%
0#
#9000
1#
#10000
0#
#11000
1)
1#
#12000
1%
0#
#13000
0!
0'
1#
