rtl/instr_mem.v
module instr_mem(input [31:0] addr, 
                 output reg [31:0] read_data
                );

    reg [31:0] ROM[0:31];
        initial
            $readmemh("sim/files/file.dat", ROM);
           
        always @(*) begin
             read_data = ROM[addr >> 2];
         end
endmodule

tb/units/tb_instr_mem.sv
`timescale 1ns/1ps

module instr_mem_tb;

    logic [31:0] addr, read_data;


    instr_mem uut(.addr(addr),
                   .read_data(read_data));

    initial begin

        $dumpfile("sim/waves/instr_mem.vcd");
        $dumpvars(0,  instr_mem_tb);

        for (int i = 0; i < 32; i++) begin
            addr = i << 2;  
            #1;

            assert(read_data === uut.ROM[i])
                $display("PASS addr=%h data=%h",
                        addr, read_data);
            else
                $error("Mismatch at address %h", addr);
        end
end

endmodule

sim/waves/instr_mem.vcd
$date
	Thu Jul  9 17:22:01 2026
$end
$version
	Icarus Verilog
$end
$timescale
	1ps
$end
$scope module instr_mem_tb $end
$var wire 32 ! read_data [31:0] $end
$var reg 32 " addr [31:0] $end
$scope module uut $end
$var wire 32 # addr [31:0] $end
$var reg 32 $ read_data [31:0] $end
$upscope $end
$scope begin $ivl_for_loop0 $end
$var integer 32 % i [31:0] $end
$upscope $end
$upscope $end
$enddefinitions $end
$comment Show the parameter values. $end
$dumpall
$end
#0
$dumpvars
b0 %
b10100011111100011100100000101011 $
b0 #
b0 "
b10100011111100011100100000101011 !
$end
#1000
b10000000000000000010011 !
b10000000000000000010011 $
b100 "
b100 #
b1 %
#2000
b1111011001010011110010011010000 !
b1111011001010011110010011010000 $
b1000 "
b1000 #
b10 %
#3000
b11111100000111010100100101100 !
b11111100000111010100100101100 $
b1100 "
b1100 #
b11 %
#4000
b11000000010011010111111010010001 !
b11000000010011010111111010010001 $
b10000 "
b10000 #
b100 %
#5000
b0 !
b0 $
b10100 "
b10100 #
b101 %
#6000
b10011010000100101111011010111000 !
b10011010000100101111011010111000 $
b11000 "
b11000 #
b110 %
#7000
b1010011111010000111110000100001 !
b1010011111010000111110000100001 $
b11100 "
b11100 #
b111 %
#8000
b11110000101000110100110101100101 !
b11110000101000110100110101100101 $
b100000 "
b100000 #
b1000 %
#9000
b1101100100100011011001000000111 !
b1101100100100011011001000000111 $
b100100 "
b100100 #
b1001 %
#10000
b10010100001111111101000111110 !
b10010100001111111101000111110 $
b101000 "
b101000 #
b1010 %
#11000
b11010100010111001000100100000001 !
b11010100010111001000100100000001 $
b101100 "
b101100 #
b1011 %
#12000
b10000111101100111110011000100000 !
b10000111101100111110011000100000 $
b110000 "
b110000 #
b1100 %
#13000
b111111000010101001000111001101 !
b111111000010101001000111001101 $
b110100 "
b110100 #
b1101 %
#14000
b11101000000110110100111101110010 !
b11101000000110110100111101110010 $
b111000 "
b111000 #
b1110 %
#15000
b100101110101101100000000111001 !
b100101110101101100000000111001 $
b111100 "
b111100 #
b1111 %
#16000
b10110111101010000100111000010101 !
b10110111101010000100111000010101 $
b1000000 "
b1000000 #
b10000 %
#17000
b1100100100111111100010100110 !
b1100100100111111100010100110 $
b1000100 "
b1000100 #
b10001 %
#18000
b10010001110111100101001001110100 !
b10010001110111100101001001110100 $
b1001000 "
b1001000 #
b10010 %
#19000
b1001010011001111011001111110000 !
b1001010011001111011001111110000 $
b1001100 "
b1001100 #
b10011 %
#20000
b11111000001011000001110101101001 !
b11111000001011000001110101101001 $
b1010000 "
b1010000 #
b10100 %
#21000
b110110111010010000101010110100 !
b110110111010010000101010110100 $
b1010100 "
b1010100 #
b10101 %
#22000
b11000111000111111000010001010010 !
b11000111000111111000010001010010 $
b1011000 "
b1011000 #
b10110 %
#23000
b1011101000000111110100110111000 !
b1011101000000111110100110111000 $
b1011100 "
b1011100 #
b10111 %
#24000
b10101000111101000110001000010000 !
b10101000111101000110001000010000 $
b1100000 "
b1100000 #
b11000 %
#25000
b11001101111000111001101011101 !
b11001101111000111001101011101 $
b1100100 "
b1100100 #
b11001 %
#26000
b11100000010010101001011011000011 !
b11100000010010101001011011000011 $
b1101000 "
b1101000 #
b11010 %
#27000
b1110010110110000001111100000101 !
b1110010110110000001111100000101 $
b1101100 "
b1101100 #
b11011 %
#28000
b10110011011011100100101010010111 !
b10110011011011100100101010010111 $
b1110000 "
b1110000 #
b11100 %
#29000
b1000111100101100011011010001 !
b1000111100101100011011010001 $
b1110100 "
b1110100 #
b11101 %
#30000
b11001111010101111010100000110000 !
b11001111010101111010100000110000 $
b1111000 "
b1111000 #
b11110 %
#31000
b1100100000110011110101101010010 !
b1100100000110011110101101010010 $
b1111100 "
b1111100 #
b11111 %
#32000
b100000 %
