rtl/pc.v
module pc(input clk, reset, en,
          input[31:0] data,
          output reg [31:0] q
          );

    always @(posedge clk or posedge reset) begin
        if (reset) 
            q <= 0;

        else if (en) 
            q <= data;
    end

endmodule

tb/units/tb_pc.v
`timescale 1ns/1ps

module pc_tb;

reg clk, reset, en;
reg [31:0] data;
wire [31:0] q;

pc uut(.clk(clk), .reset(reset), .en(en), .data(data), .q(q));

    initial begin
    clk = 0;
    end

    always #5 clk = ~clk;

    // reset 
    initial begin
    reset = 1;
    #10;
    reset = 0;
    end


    initial begin

        $dumpfile("sim/waves/pc.vcd");
        $dumpvars(0, pc_tb);

        en  = 0;
        data  = 0;

        #10;
        en = 1; data = 32'hFFFFFFF6; #10;
        en = 0; data = 32'hFFFFFFF7; #10;
        reset = 1; #10;
        reset = 0;
        en = 0; data = 9; #10;
        en = 1; #10;


        $finish;
    end

endmodule

sim/waves/pc.vcd
$date
	Tue May  5 02:08:52 2026
$end
$version
	Icarus Verilog
$end
$timescale
	1ps
$end
$scope module pc_tb $end
$var wire 32 ! q [31:0] $end
$var reg 1 " clk $end
$var reg 32 # data [31:0] $end
$var reg 1 $ en $end
$var reg 1 % reset $end
$scope module uut $end
$var wire 1 " clk $end
$var wire 32 & data [31:0] $end
$var wire 1 $ en $end
$var wire 1 % reset $end
$var reg 32 ' q [31:0] $end
$upscope $end
$upscope $end
$enddefinitions $end
$comment Show the parameter values. $end
$dumpall
$end
#0
$dumpvars
b0 '
b0 &
1%
0$
b0 #
0"
b0 !
$end
#5000
1"
#10000
0"
b11111111111111111111111111110110 #
b11111111111111111111111111110110 &
1$
0%
#15000
b11111111111111111111111111110110 !
b11111111111111111111111111110110 '
1"
#20000
0"
b11111111111111111111111111110111 #
b11111111111111111111111111110111 &
0$
#25000
1"
#30000
b0 !
b0 '
0"
1%
#35000
1"
#40000
0"
b1001 #
b1001 &
0%
#45000
1"
#50000
0"
1$
#55000
b1001 !
b1001 '
1"
