rtl/register.v
module reg_file(input clk, reg_write_en, 
                input[3:0] reg_addr_1, reg_addr_2, write_addr,
                input[31:0] write_data, reg_addr_15,
                output [31:0] read_data_1, read_data_2
                );

    reg [31:0] reg_file[14:0];
    

    always @(posedge clk) begin
        if (reg_write_en) 
            reg_file[write_addr] <= write_data;
    end
            
    assign read_data_1 = (reg_addr_1 == 4'b1111) ? reg_addr_15 : reg_file[reg_addr_1];
    assign read_data_2 = (reg_addr_2 == 4'b1111) ? reg_addr_15 : reg_file[reg_addr_2];

endmodule

tb/units/tb_register.v
`timescale 1ns/1ps

module reg_file_tb;

    reg clk, reg_write_en;
    reg [3:0] reg_addr_1, reg_addr_2, write_addr;
    reg [31:0] write_data, reg_addr_15;
    wire [31:0] read_data_1, read_data_2;

    initial clk = 0;
    always #1 clk = ~clk;

    reg_file uut(.clk(clk), .reg_write_en(reg_write_en), 
                .reg_addr_1(reg_addr_1),
                .reg_addr_2(reg_addr_2), 
                .write_addr(write_addr), 
                .write_data(write_data), 
                .reg_addr_15(reg_addr_15),
                .read_data_1(read_data_1), 
                .read_data_2(read_data_2));

    initial begin

        $dumpfile("sim/waves/register.vcd");
        $dumpvars(0, reg_file_tb);
        reg_addr_15 = 32'hF;
        write_data = 32'hFC;
        reg_write_en = 0;
        reg_addr_1 = 0; reg_addr_2 = 0; 
        write_addr = 0;

        @(posedge clk); reg_write_en = 1; write_addr = 0; write_data = 32'h2; #2; // read_data_1 = 0, read_data_2 = 0
        @(posedge clk); reg_write_en = 1; write_addr = 1;  write_data = 32'hFA; #2;  // read_data_1 = 0, read_data_2 = 0
        @(posedge clk); reg_write_en = 0; reg_addr_1 = 0; reg_addr_2 = 1; #2; // read_data_1 =  32'hFC, read_data_2 = 32'hFA
        reg_addr_1 = 15;  reg_addr_2 = 0; #2; // read_data_1 =  32'hF, read_data_2 = 32'h2

       //reg_addr_1 = 4'h3; reg_addr_2 = 4'hE;

        uut.reg_file[0] = 32'h7;
        uut.reg_file[1] = 32'h5;
        uut.reg_file[3] = 32'hC;
        uut.reg_file[14] = 32'hE;
        
        reg_addr_1 = 4'b0011; reg_addr_2 = 4'b1110;
        #2;
        
        $display("RA1 is %d", reg_addr_1);
        $display("RA2 is %d", reg_addr_2);
        

        if (read_data_1 != 32'hC)
           $error("Register address path 1 broken");
        $display("time=%0t src_1 value is %h", $time, read_data_1);
        
        if (read_data_2 != 32'hE)
            $error("Register address path 2 broken");
        $display("time=%0t src_2 value is %h", $time, read_data_2);


        @(posedge clk);
        reg_write_en = 1;
        write_addr   = 4'h1;
        write_data   = 32'h32;


        reg_addr_2 = 4'h1; //  read_data_1 =  32'hC, read_data_2 = 32'h32
        @(posedge clk); 
        reg_write_en = 0;
        #1;

        if (read_data_2 != 32'h32)
            $error("overwrite failed");
            $display("time=%0t src_2 value is %h", $time, read_data_2);

        $finish;

    end


endmodule

sim/waves/register.vcd
$date
	Wed May 13 03:33:39 2026
$end
$version
	Icarus Verilog
$end
$timescale
	1ps
$end
$scope module reg_file_tb $end
$var wire 32 ! read_data_2 [31:0] $end
$var wire 32 " read_data_1 [31:0] $end
$var reg 1 # clk $end
$var reg 4 $ reg_addr_1 [3:0] $end
$var reg 32 % reg_addr_15 [31:0] $end
$var reg 4 & reg_addr_2 [3:0] $end
$var reg 1 ' reg_write_en $end
$var reg 4 ( write_addr [3:0] $end
$var reg 32 ) write_data [31:0] $end
$scope module uut $end
$var wire 1 # clk $end
$var wire 4 * reg_addr_1 [3:0] $end
$var wire 32 + reg_addr_15 [31:0] $end
$var wire 4 , reg_addr_2 [3:0] $end
$var wire 1 ' reg_write_en $end
$var wire 4 - write_addr [3:0] $end
$var wire 32 . write_data [31:0] $end
$var wire 32 / read_data_2 [31:0] $end
$var wire 32 0 read_data_1 [31:0] $end
$upscope $end
$upscope $end
$enddefinitions $end
$comment Show the parameter values. $end
$dumpall
$end
#0
$dumpvars
bx 0
bx /
b11111100 .
b0 -
b0 ,
b1111 +
b0 *
b11111100 )
b0 (
0'
b0 &
b1111 %
b0 $
0#
bx "
bx !
$end
#1000
b10 "
b10 0
b10 !
b10 /
b10 )
b10 .
1'
1#
#2000
0#
#3000
b11111010 )
b11111010 .
b1 (
b1 -
1#
#4000
0#
#5000
b11111010 !
b11111010 /
b1 &
b1 ,
0'
1#
#6000
0#
#7000
b10 !
b10 /
b1111 "
b1111 0
1#
b0 &
b0 ,
b1111 $
b1111 *
#8000
0#
#9000
b1100 "
b1100 0
b1110 !
b1110 /
1#
b1110 &
b1110 ,
b11 $
b11 *
#10000
0#
#11000
b110010 !
b110010 /
b1 &
b1 ,
b110010 )
b110010 .
1'
1#
#12000
0#
#13000
0'
1#
